Workbook

Sheet Cover
A3: Track
A4: 1 | B4: =HYPERLINK("#'Dashboard'!A1","Dashboard") -> Dashboard | C4: money · people · risks
A5: 2 | B5: =HYPERLINK("#'Channel_Pivot'!A1","Channel_Pivot") -> Channel_Pivot | C5: which channel pays
A6: 3 | B6: =HYPERLINK("#'First30'!A1","First30") -> First30 | C6: start here
A7: 4 | B7: =HYPERLINK("#'Gantt'!A1","Gantt") -> Gantt | C7: overall plan
A8: 5 | B8: =HYPERLINK("#'Sales2027'!A1","Sales2027") -> Sales2027 | C8: Sales Plan 2027
A9: 6 | B9: =HYPERLINK("#'PnL2027'!A1","PnL2027") -> PnL2027 | C9: costs + net
A10: Work
A11: 7 | B11: =HYPERLINK("#'Leads'!A1","Leads") -> Leads | C11: pipeline
A12: 8 | B12: =HYPERLINK("#'Trials'!A1","Trials") -> Trials | C12: booking + outcome
A13: 9 | B13: =HYPERLINK("#'Invoices'!A1","Invoices") -> Invoices | C13: bill + collect
A14: 10 | B14: =HYPERLINK("#'Students'!A1","Students") -> Students | C14: credits left
A15: 11 | B15: =HYPERLINK("#'Makeup_Churn'!A1","Makeup_Churn") -> Makeup_Churn | C15: who drifts
A16: 12 | B16: =HYPERLINK("#'Expenses'!A1","Expenses") -> Expenses | C16: spend
A17: 13 | B17: =HYPERLINK("#'WinterCamp'!A1","WinterCamp") -> WinterCamp | C17: full
A18: 14 | B18: =HYPERLINK("#'Camp_Plan'!A1","Camp_Plan") -> Camp_Plan | C18: 6-step plan
A19: Send
A20: 15 | B20: =HYPERLINK("#'Scripts'!A1","Scripts") -> Scripts
A21: 16 | B21: =HYPERLINK("#'Send_Kit'!A1","Send_Kit") -> Send_Kit | C21: Kits
A22: 17 | B22: =HYPERLINK("#'SOP'!A1","SOP") -> SOP | C22: 8 steps daily
A23: Program
A24: 18 | B24: =HYPERLINK("#'Programs'!A1","Programs") -> Programs | C24: Programs
A25: 19 | B25: =HYPERLINK("#'Exhibitions'!A1","Exhibitions") -> Exhibitions | C25: Exhibitions
A26: 20 | B26: =HYPERLINK("#'Certificates'!A1","Certificates") -> Certificates | C26: Certificates Tracker
A27: 21 | B27: =HYPERLINK("#'Certificate'!A1","Certificate") -> Certificate | C27: print certificate
A28: 22 | B28: =HYPERLINK("#'Calendar'!A1","Calendar") -> Calendar | C28: year calendar
A29: 23 | B29: =HYPERLINK("#'Showcase'!A1","Showcase") -> Showcase | C29: art party plan
A30: 24 | B30: =HYPERLINK("#'BirthdayWS'!A1","BirthdayWS") -> BirthdayWS | C30: birthday plan
A31: 25 | B31: =HYPERLINK("#'HalloweenPlan'!A1","HalloweenPlan") -> HalloweenPlan | C31: pumpkin plan
A32: Assets
A33: 26 | B33: =HYPERLINK("#'Assets'!A1","Assets") -> Assets | C33: Assets Control
A34: 27 | B34: =HYPERLINK("#'PDF_List'!A1","PDF_List") -> PDF_List | C34: missing list
A35: 28 | B35: =HYPERLINK("#'Flyer'!A1","Flyer") -> Flyer | C35: trial flyer
A36: 29 | B36: =HYPERLINK("#'Halloween'!A1","Halloween") -> Halloween | C36: pumpkin flyer
A37: 30 | B37: =HYPERLINK("#'ForFun_EN'!A1","ForFun_EN") -> ForFun_EN | C37: for fun
A38: 31 | B38: =HYPERLINK("#'Events'!A1","Events") -> Events | C38: events + gifts
A39: 32 | B39: =HYPERLINK("#'Brand'!A1","Brand") -> Brand | C39: logo + sign-offs
A40: 33 | B40: =HYPERLINK("#'Invoice_Poster'!A1","Invoice_Poster") -> Invoice_Poster | C40: print invoice
A41: 34 | B41: =HYPERLINK("#'Consent_Poster'!A1","Consent_Poster") -> Consent_Poster | C41: print consent
A42: 35 | B42: =HYPERLINK("#'Survey_Poster'!A1","Survey_Poster") -> Survey_Poster | C42: print
A43: Risk
A44: 36 | B44: =HYPERLINK("#'Access'!A1","Access") -> Access | C44: who edits
A45: 37 | B45: =HYPERLINK("#'Consents'!A1","Consents") -> Consents | C45: sign first
A46: 38 | B46: =HYPERLINK("#'Approvals'!A1","Approvals") -> Approvals | C46: approve first
A47: 39 | B47: =HYPERLINK("#'Offboarding'!A1","Offboarding") -> Offboarding | C47: exit flow
A48: 40 | B48: =HYPERLINK("#'AntiFraud'!A1","AntiFraud") -> AntiFraud | C48: scam defense
A49: 41 | B49: =HYPERLINK("#'Tasklist'!A1","Tasklist") -> Tasklist | C49: scope + hours
A50: 42 | B50: =HYPERLINK("#'Compliance'!A1","Compliance") -> Compliance | C50: law + red lines

Sheet Dashboard
A1: Dashboard | D1: =HYPERLINK("#'Cover'!A1","←") -> ←
A2: Item | B2: Amount (¥) | C2: Notes
A3: Month revenue (paid) | B3: =SUMIF(Invoices!I3:I34,"Paid",Invoices!H3:H34) -> 8000
A4: Outstanding (unpaid) | B4: =SUMIF(Invoices!I3:I34,"Unpaid",Invoices!H3:H34) -> 0 | C4: ¥ — chase now
A5: Other expenses | B5: =SUM(Expenses!D3:D100) -> 0 | C5: ¥ — auto from Expenses
A6: Referral payout 10% | B6: =B3*0.1 -> 800 | C6: ¥
A7: Hospitality 3% | B7: =B3*0.03 -> 240 | C7: ¥
A8: Net balance | B8: =B3-B4-B5-B6-B7 -> 6960 | C8: ¥ — revenue minus all
A9: Active students | B9: =COUNTA(Students!A3:A100) -> 5 | C9: kids
A10: Open leads | B10: =COUNTIF(Leads!G3:G100,"Contacting")+COUNTIF(Leads!G3:G100,"Trial booked") -> 1 | C10: families
A11: Trial→enrolment | B11: =IFERROR(COUNTIF(Trials!F3:F100,"Enrolled")/COUNTA(Trials!A3:A100),0) -> 0.5 | C11: target 50%
A12: Renewals due | B12: =COUNTIF(Students!J3:J100,"Renew now") -> 0 | C12: kids — see Students
A13: Renew soon (4 left — act early) | B13: =COUNTIF(Students!J3:J100,"Renew soon") -> 0 | C13: families — talk before the last 2
A14: Churn risks | B14: =COUNTIF(Makeup_Churn!F3:F100,"At risk — talk now") -> 0 | C14: families
A15: Camp weeks full | B15: =COUNTIF(WinterCamp!G3:G100,"Full") -> 0 | C15: weeks ≥4 kids
A16: Renew now list | B16: =IF(COUNTIF(Students!J3:J100,"Renew now")=0,"--",INDEX(Students!B3:B100,MATCH("Renew now",Students!J3:J100,0))&" +"&COUNTIF(Students!J3:J100,"Renew now")&" kids") -> -- | C16: List (auto in modern WPS; else see red rows)
A17: Churn watchlist | B17: =IF(COUNTIF(Makeup_Churn!F3:F100,"At risk — talk now")=0,"--",INDEX(Makeup_Churn!A3:A100,MATCH("At risk — talk now",Makeup_Churn!F3:F100,0))&" +"&COUNTIF(Makeup_Churn!F3:F100,"At risk — talk now")&" families") -> -- | C17: List (auto in modern WPS; else see red rows)
A18: Outstanding detail | B18: =IF(COUNTIF(Invoices!I3:I34,"Unpaid")=0,"--",INDEX(Invoices!C3:C34,MATCH("Unpaid",Invoices!I3:I34,0))&" +"&COUNTIF(Invoices!I3:I34,"Unpaid")&" invoices") -> -- | C18: Detail (auto; else see Unpaid rows)
A19: Today's list (auto) | D19: Done?
A20: Renew now: call red rows in Students | B20: =COUNTIF(Students!J3:J100,"Renew now")&" kids" -> 0 kids
A21: At risk: talk to red rows in Makeup_Churn | B21: =COUNTIF(Makeup_Churn!F3:F100,"At risk — talk now")&" families" -> 0 families
A22: Unpaid: chase Unpaid rows in Invoices | B22: =COUNTIF(Invoices!I3:I34,"Unpaid")&" invoices" -> 0 invoices
A24: Targets vs Actual (meeting numbers)
A25: Metric | B25: Target | C25: Actual | D25: Gap
A26: Students / month | B26: 15 | C26: =COUNTA(Students!A3:A100) -> 5 | D26: =C25-B25 -> #VALUE!
A27: Trial conversion | B27: 0.5 | C27: =IFERROR(COUNTIF(Trials!F3:F100,"Enrolled")/MAX(1,COUNTA(Trials!A3:A100)),0) -> 0.5 | D27: =C26-B26 -> -10
A28: Camp weeks full | B28: 2 | C28: =COUNTIF(WinterCamp!G3:G100,"Full") -> 0 | D28: =C27-B27 -> 0
A29: Renewals due (want 0) | B29: 0 | C29: =COUNTIF(Students!J3:J100,"Renew now") -> 0 | D29: =C28-B28 -> -2
A30: Churn risks (want 0) | B30: 0 | C30: =COUNTIF(Makeup_Churn!F3:F100,"At risk — talk now") -> 0 | D30: =C29-B29 -> 0
A31: Unpaid bills (want 0) | B31: 0 | C31: =COUNTIF(Invoices!I3:I34,"Unpaid") -> 0 | D31: =C30-B30 -> 0
A32: Open items (want 0): renewals, risks, unpaid above. | B32: 24 hours | C32: Target (meeting)

Sheet Students
A1: Students & Class Credits | M1: =HYPERLINK("#'Cover'!A1","←") -> ←
A2: ID | B2: Name | C2: Age | D2: School | E2: WeChat | F2: Package | G2: Total | H2: Used | I2: Left | J2: Renew flag | K2: From trial | L2: Absences
A3: STU-01 | B3: Josh D1 | C3: 7 | D3: Dulwich | F3: Semester+1 | G3: 20 | H3: 6 | I3: =IF(G3="","",G3-H3) -> 14 | J3: =IF(I3="","",IF(I3<=2,"Renew now",IF(I3<=4,"Renew soon","OK"))) -> OK | K3: =IF(B3="","",IFERROR(INDEX(Trials!A$3:A$50,MATCH("*"&B3&"*",Trials!C$3:C$50,0)),"")) -> TR-01
A4: STU-02 | B4: Josh D2 | C4: 6 | D4: Dulwich | F4: Semester | G4: 12 | H4: 0 | I4: =IF(G4="","",G4-H4) -> 12 | J4: =IF(I4="","",IF(I4<=2,"Renew now",IF(I4<=4,"Renew soon","OK"))) -> OK | K4: =IF(B4="","",IFERROR(INDEX(Trials!A$3:A$50,MATCH("*"&B4&"*",Trials!C$3:C$50,0)),"")) | L4: =IF(B4="","",SUMIF(Makeup_Churn!A$3:A$100,B4,Makeup_Churn!C$3:C$100)) -> 0
A5: STU-03 | B5: Charlotte | C5: 5 | D5: Dulwich | F5: Semester | G5: 12 | H5: 0 | I5: =IF(G5="","",G5-H5) -> 12 | J5: =IF(I5="","",IF(I5<=2,"Renew now",IF(I5<=4,"Renew soon","OK"))) -> OK | K5: =IF(B5="","",IFERROR(INDEX(Trials!A$3:A$50,MATCH("*"&B5&"*",Trials!C$3:C$50,0)),"")) | L5: =IF(B5="","",SUMIF(Makeup_Churn!A$3:A$100,B5,Makeup_Churn!C$3:C$100)) -> 0
A6: STU-04 | B6: William | C6: 7 | D6: Dulwich | F6: Semester | G6: 12 | H6: 0 | I6: =IF(G6="","",G6-H6) -> 12 | J6: =IF(I6="","",IF(I6<=2,"Renew now",IF(I6<=4,"Renew soon","OK"))) -> OK | K6: =IF(B6="","",IFERROR(INDEX(Trials!A$3:A$50,MATCH("*"&B6&"*",Trials!C$3:C$50,0)),"")) | L6: =IF(B6="","",SUMIF(Makeup_Churn!A$3:A$100,B6,Makeup_Churn!C$3:C$100)) -> 0
A7: STU-05 | B7: Daphne | C7: 9 | D7: YCIS | F7: 18-class | G7: 18 | H7: 4 | I7: =IF(G7="","",G7-H7) -> 14 | J7: =IF(I7="","",IF(I7<=2,"Renew now",IF(I7<=4,"Renew soon","OK"))) -> OK | K7: =IF(B7="","",IFERROR(INDEX(Trials!A$3:A$50,MATCH("*"&B7&"*",Trials!C$3:C$50,0)),"")) | L7: =IF(B7="","",SUMIF(Makeup_Churn!A$3:A$100,B7,Makeup_Churn!C$3:C$100)) -> 0
I8: =IF(G8="","",G8-H8) | J8: =IF(I8="","",IF(I8<=2,"Renew now",IF(I8<=4,"Renew soon","OK"))) | K8: =IF(B8="","",IFERROR(INDEX(Trials!A$3:A$50,MATCH("*"&B8&"*",Trials!C$3:C$50,0)),"")) | L8: =IF(B8="","",SUMIF(Makeup_Churn!A$3:A$100,B8,Makeup_Churn!C$3:C$100))
I9: =IF(G9="","",G9-H9) | J9: =IF(I9="","",IF(I9<=2,"Renew now",IF(I9<=4,"Renew soon","OK"))) | K9: =IF(B9="","",IFERROR(INDEX(Trials!A$3:A$50,MATCH("*"&B9&"*",Trials!C$3:C$50,0)),"")) | L9: =IF(B9="","",SUMIF(Makeup_Churn!A$3:A$100,B9,Makeup_Churn!C$3:C$100))
I10: =IF(G10="","",G10-H10) | J10: =IF(I10="","",IF(I10<=2,"Renew now",IF(I10<=4,"Renew soon","OK"))) | K10: =IF(B10="","",IFERROR(INDEX(Trials!A$3:A$50,MATCH("*"&B10&"*",Trials!C$3:C$50,0)),"")) | L10: =IF(B10="","",SUMIF(Makeup_Churn!A$3:A$100,B10,Makeup_Churn!C$3:C$100))
I11: =IF(G11="","",G11-H11) | J11: =IF(I11="","",IF(I11<=2,"Renew now",IF(I11<=4,"Renew soon","OK"))) | K11: =IF(B11="","",IFERROR(INDEX(Trials!A$3:A$50,MATCH("*"&B11&"*",Trials!C$3:C$50,0)),"")) | L11: =IF(B11="","",SUMIF(Makeup_Churn!A$3:A$100,B11,Makeup_Churn!C$3:C$100))
I12: =IF(G12="","",G12-H12) | J12: =IF(I12="","",IF(I12<=2,"Renew now",IF(I12<=4,"Renew soon","OK"))) | K12: =IF(B12="","",IFERROR(INDEX(Trials!A$3:A$50,MATCH("*"&B12&"*",Trials!C$3:C$50,0)),"")) | L12: =IF(B12="","",SUMIF(Makeup_Churn!A$3:A$100,B12,Makeup_Churn!C$3:C$100))
I13: =IF(G13="","",G13-H13) | J13: =IF(I13="","",IF(I13<=2,"Renew now",IF(I13<=4,"Renew soon","OK"))) | K13: =IF(B13="","",IFERROR(INDEX(Trials!A$3:A$50,MATCH("*"&B13&"*",Trials!C$3:C$50,0)),"")) | L13: =IF(B13="","",SUMIF(Makeup_Churn!A$3:A$100,B13,Makeup_Churn!C$3:C$100))
I14: =IF(G14="","",G14-H14) | J14: =IF(I14="","",IF(I14<=2,"Renew now",IF(I14<=4,"Renew soon","OK"))) | K14: =IF(B14="","",IFERROR(INDEX(Trials!A$3:A$50,MATCH("*"&B14&"*",Trials!C$3:C$50,0)),"")) | L14: =IF(B14="","",SUMIF(Makeup_Churn!A$3:A$100,B14,Makeup_Churn!C$3:C$100))
I15: =IF(G15="","",G15-H15) | J15: =IF(I15="","",IF(I15<=2,"Renew now",IF(I15<=4,"Renew soon","OK"))) | K15: =IF(B15="","",IFERROR(INDEX(Trials!A$3:A$50,MATCH("*"&B15&"*",Trials!C$3:C$50,0)),"")) | L15: =IF(B15="","",SUMIF(Makeup_Churn!A$3:A$100,B15,Makeup_Churn!C$3:C$100))
I16: =IF(G16="","",G16-H16) | J16: =IF(I16="","",IF(I16<=2,"Renew now",IF(I16<=4,"Renew soon","OK"))) | K16: =IF(B16="","",IFERROR(INDEX(Trials!A$3:A$50,MATCH("*"&B16&"*",Trials!C$3:C$50,0)),"")) | L16: =IF(B16="","",SUMIF(Makeup_Churn!A$3:A$100,B16,Makeup_Churn!C$3:C$100))
I17: =IF(G17="","",G17-H17) | J17: =IF(I17="","",IF(I17<=2,"Renew now",IF(I17<=4,"Renew soon","OK"))) | K17: =IF(B17="","",IFERROR(INDEX(Trials!A$3:A$50,MATCH("*"&B17&"*",Trials!C$3:C$50,0)),"")) | L17: =IF(B17="","",SUMIF(Makeup_Churn!A$3:A$100,B17,Makeup_Churn!C$3:C$100))
I18: =IF(G18="","",G18-H18) | J18: =IF(I18="","",IF(I18<=2,"Renew now",IF(I18<=4,"Renew soon","OK"))) | K18: =IF(B18="","",IFERROR(INDEX(Trials!A$3:A$50,MATCH("*"&B18&"*",Trials!C$3:C$50,0)),"")) | L18: =IF(B18="","",SUMIF(Makeup_Churn!A$3:A$100,B18,Makeup_Churn!C$3:C$100))
I19: =IF(G19="","",G19-H19) | J19: =IF(I19="","",IF(I19<=2,"Renew now",IF(I19<=4,"Renew soon","OK"))) | K19: =IF(B19="","",IFERROR(INDEX(Trials!A$3:A$50,MATCH("*"&B19&"*",Trials!C$3:C$50,0)),"")) | L19: =IF(B19="","",SUMIF(Makeup_Churn!A$3:A$100,B19,Makeup_Churn!C$3:C$100))
... I32: =IF(G32="","",G32-H32) | J32: =IF(I32="","",IF(I32<=2,"Renew now",IF(I32<=4,"Renew soon","OK"))) | K32: =IF(B32="","",IFERROR(INDEX(Trials!A$3:A$50,MATCH("*"&B32&"*",Trials!C$3:C$50,0)),"")) | L32: =IF(B32="","",SUMIF(Makeup_Churn!A$3:A$100,B32,Makeup_Churn!C$3:C$100))
I33: =IF(G33="","",G33-H33) | K33: =IF(B33="","",IFERROR(INDEX(Trials!A$3:A$50,MATCH("*"&B33&"*",Trials!C$3:C$50,0)),""))
I34: =IF(G34="","",G34-H34) | K34: =IF(B34="","",IFERROR(INDEX(Trials!A$3:A$50,MATCH("*"&B34&"*",Trials!C$3:C$50,0)),""))
I35: =IF(G35="","",G35-H35) | K35: =IF(B35="","",IFERROR(INDEX(Trials!A$3:A$50,MATCH("*"&B35&"*",Trials!C$3:C$50,0)),""))
I36: =IF(G36="","",G36-H36) | K36: =IF(B36="","",IFERROR(INDEX(Trials!A$3:A$50,MATCH("*"&B36&"*",Trials!C$3:C$50,0)),""))
I37: =IF(G37="","",G37-H37) | K37: =IF(B37="","",IFERROR(INDEX(Trials!A$3:A$50,MATCH("*"&B37&"*",Trials!C$3:C$50,0)),""))
I38: =IF(G38="","",G38-H38) | K38: =IF(B38="","",IFERROR(INDEX(Trials!A$3:A$50,MATCH("*"&B38&"*",Trials!C$3:C$50,0)),""))
I39: =IF(G39="","",G39-H39) | K39: =IF(B39="","",IFERROR(INDEX(Trials!A$3:A$50,MATCH("*"&B39&"*",Trials!C$3:C$50,0)),""))
I40: =IF(G40="","",G40-H40) | K40: =IF(B40="","",IFERROR(INDEX(Trials!A$3:A$50,MATCH("*"&B40&"*",Trials!C$3:C$50,0)),""))
I41: =IF(G41="","",G41-H41) | K41: =IF(B41="","",IFERROR(INDEX(Trials!A$3:A$50,MATCH("*"&B41&"*",Trials!C$3:C$50,0)),""))
I42: =IF(G42="","",G42-H42) | K42: =IF(B42="","",IFERROR(INDEX(Trials!A$3:A$50,MATCH("*"&B42&"*",Trials!C$3:C$50,0)),""))
I43: =IF(G43="","",G43-H43) | K43: =IF(B43="","",IFERROR(INDEX(Trials!A$3:A$50,MATCH("*"&B43&"*",Trials!C$3:C$50,0)),""))
I44: =IF(G44="","",G44-H44) | K44: =IF(B44="","",IFERROR(INDEX(Trials!A$3:A$50,MATCH("*"&B44&"*",Trials!C$3:C$50,0)),""))
... I100: =IF(G100="","",G100-H100) | K100: =IF(B100="","",IFERROR(INDEX(Trials!A$3:A$50,MATCH("*"&B100&"*",Trials!C$3:C$50,0)),""))

Sheet Leads
A1: Leads | M1: =HYPERLINK("#'Cover'!A1","←") -> ←
A2: Lead ID | B2: Parent | C2: Child / Age | D2: School | E2: Source | F2: CCA? | G2: Status | H2: Next step | I2: Last follow-up | J2: Introduced by | K2: Owner | L2: First-touch script
A3: LEAD-01 | B3: Josh's dad | C3: Josh D1, 7 | D3: Dulwich | E3: Referral | F3: No | G3: Enrolled | H3: Collect 4-kid fees
A4: LEAD-02 | B4: Pending A | E4: CCA showcase | F4: Yes | G4: Contacting | H4: Invite to visit | K4: Studio official | L4: =IF(F4="Yes",IFERROR(VLOOKUP("C1",Scripts!A$3:D$60,3,FALSE),""),"") -> You're warmly invited: our end-of-term mini exhibition opens Saturday afternoon, and [child] has work in it. Come hear them talk it through for five minutes — grandparents very welcome too. Afterwards, come upstairs and see the studio.
L5: =IF(F5="Yes",IFERROR(VLOOKUP("C1",Scripts!A$3:D$60,3,FALSE),""),"")
L6: =IF(F6="Yes",IFERROR(VLOOKUP("C1",Scripts!A$3:D$60,3,FALSE),""),"")
L7: =IF(F7="Yes",IFERROR(VLOOKUP("C1",Scripts!A$3:D$60,3,FALSE),""),"")
L8: =IF(F8="Yes",IFERROR(VLOOKUP("C1",Scripts!A$3:D$60,3,FALSE),""),"")
L9: =IF(F9="Yes",IFERROR(VLOOKUP("C1",Scripts!A$3:D$60,3,FALSE),""),"")
L10: =IF(F10="Yes",IFERROR(VLOOKUP("C1",Scripts!A$3:D$60,3,FALSE),""),"")
L11: =IF(F11="Yes",IFERROR(VLOOKUP("C1",Scripts!A$3:D$60,3,FALSE),""),"")
L12: =IF(F12="Yes",IFERROR(VLOOKUP("C1",Scripts!A$3:D$60,3,FALSE),""),"")
L13: =IF(F13="Yes",IFERROR(VLOOKUP("C1",Scripts!A$3:D$60,3,FALSE),""),"")
L14: =IF(F14="Yes",IFERROR(VLOOKUP("C1",Scripts!A$3:D$60,3,FALSE),""),"")
L15: =IF(F15="Yes",IFERROR(VLOOKUP("C1",Scripts!A$3:D$60,3,FALSE),""),"")
L16: =IF(F16="Yes",IFERROR(VLOOKUP("C1",Scripts!A$3:D$60,3,FALSE),""),"")
... L100: =IF(F100="Yes",IFERROR(VLOOKUP("C1",Scripts!A$3:D$60,3,FALSE),""),"")

Sheet Trials
A1: Trials | K1: =HYPERLINK("#'Cover'!A1","←") -> ←
A2: Trial ID | B2: Lead ID | C2: Child | D2: Date | E2: Attended | F2: Outcome | G2: No-enrol reason | H2: Script | I2: Script CN | J2: Script EN
A3: TR-01 | B3: LEAD-01 | C3: =IF(B3="","",IFERROR(VLOOKUP(B3,Leads!A$3:C$100,3,FALSE),"")) -> Josh D1, 7 | D3: 2026-10-18 | E3: Attended | F3: Enrolled | H3: T1
A4: TR-02 | B4: LEAD-02 | C4: =IF(B4="","",IFERROR(VLOOKUP(B4,Leads!A$3:C$100,3,FALSE),"")) | D4: 2026-10-19 | E4: Attended | F4: Not enrolled | G4: Schedule clash | H4: T2 | I4: =IF(H4="","",IFERROR(VLOOKUP(H4,Scripts!A$3:D$60,3,FALSE),"")) -> No pressure at all — art can't be rushed. If you have a moment, tell me what held you back (timing, fee, or simply not yet) so I can note it. When a camp or workshop fits, you'll hear from me first. | J4: =IF(H4="","",IFERROR(VLOOKUP(H4,Scripts!A$3:D$60,4,FALSE),"")) -> 完全没关系，艺术急不得。方便的话告诉我一声，是时间、费用，还是时机未到，我记下来。以后有合适的营或工坊，我第一个告诉您。
C5: =IF(B5="","",IFERROR(VLOOKUP(B5,Leads!A$3:C$100,3,FALSE),"")) | I5: =IF(H5="","",IFERROR(VLOOKUP(H5,Scripts!A$3:D$60,3,FALSE),"")) | J5: =IF(H5="","",IFERROR(VLOOKUP(H5,Scripts!A$3:D$60,4,FALSE),""))
C6: =IF(B6="","",IFERROR(VLOOKUP(B6,Leads!A$3:C$100,3,FALSE),"")) | I6: =IF(H6="","",IFERROR(VLOOKUP(H6,Scripts!A$3:D$60,3,FALSE),"")) | J6: =IF(H6="","",IFERROR(VLOOKUP(H6,Scripts!A$3:D$60,4,FALSE),""))
C7: =IF(B7="","",IFERROR(VLOOKUP(B7,Leads!A$3:C$100,3,FALSE),"")) | I7: =IF(H7="","",IFERROR(VLOOKUP(H7,Scripts!A$3:D$60,3,FALSE),"")) | J7: =IF(H7="","",IFERROR(VLOOKUP(H7,Scripts!A$3:D$60,4,FALSE),""))
C8: =IF(B8="","",IFERROR(VLOOKUP(B8,Leads!A$3:C$100,3,FALSE),"")) | I8: =IF(H8="","",IFERROR(VLOOKUP(H8,Scripts!A$3:D$60,3,FALSE),"")) | J8: =IF(H8="","",IFERROR(VLOOKUP(H8,Scripts!A$3:D$60,4,FALSE),""))
C9: =IF(B9="","",IFERROR(VLOOKUP(B9,Leads!A$3:C$100,3,FALSE),"")) | I9: =IF(H9="","",IFERROR(VLOOKUP(H9,Scripts!A$3:D$60,3,FALSE),"")) | J9: =IF(H9="","",IFERROR(VLOOKUP(H9,Scripts!A$3:D$60,4,FALSE),""))
C10: =IF(B10="","",IFERROR(VLOOKUP(B10,Leads!A$3:C$100,3,FALSE),"")) | I10: =IF(H10="","",IFERROR(VLOOKUP(H10,Scripts!A$3:D$60,3,FALSE),"")) | J10: =IF(H10="","",IFERROR(VLOOKUP(H10,Scripts!A$3:D$60,4,FALSE),""))
C11: =IF(B11="","",IFERROR(VLOOKUP(B11,Leads!A$3:C$100,3,FALSE),"")) | I11: =IF(H11="","",IFERROR(VLOOKUP(H11,Scripts!A$3:D$60,3,FALSE),"")) | J11: =IF(H11="","",IFERROR(VLOOKUP(H11,Scripts!A$3:D$60,4,FALSE),""))
C12: =IF(B12="","",IFERROR(VLOOKUP(B12,Leads!A$3:C$100,3,FALSE),"")) | I12: =IF(H12="","",IFERROR(VLOOKUP(H12,Scripts!A$3:D$60,3,FALSE),"")) | J12: =IF(H12="","",IFERROR(VLOOKUP(H12,Scripts!A$3:D$60,4,FALSE),""))
C13: =IF(B13="","",IFERROR(VLOOKUP(B13,Leads!A$3:C$100,3,FALSE),"")) | I13: =IF(H13="","",IFERROR(VLOOKUP(H13,Scripts!A$3:D$60,3,FALSE),"")) | J13: =IF(H13="","",IFERROR(VLOOKUP(H13,Scripts!A$3:D$60,4,FALSE),""))
C14: =IF(B14="","",IFERROR(VLOOKUP(B14,Leads!A$3:C$100,3,FALSE),"")) | I14: =IF(H14="","",IFERROR(VLOOKUP(H14,Scripts!A$3:D$60,3,FALSE),"")) | J14: =IF(H14="","",IFERROR(VLOOKUP(H14,Scripts!A$3:D$60,4,FALSE),""))
C15: =IF(B15="","",IFERROR(VLOOKUP(B15,Leads!A$3:C$100,3,FALSE),"")) | I15: =IF(H15="","",IFERROR(VLOOKUP(H15,Scripts!A$3:D$60,3,FALSE),"")) | J15: =IF(H15="","",IFERROR(VLOOKUP(H15,Scripts!A$3:D$60,4,FALSE),""))
C16: =IF(B16="","",IFERROR(VLOOKUP(B16,Leads!A$3:C$100,3,FALSE),"")) | I16: =IF(H16="","",IFERROR(VLOOKUP(H16,Scripts!A$3:D$60,3,FALSE),"")) | J16: =IF(H16="","",IFERROR(VLOOKUP(H16,Scripts!A$3:D$60,4,FALSE),""))
... C32: =IF(B32="","",IFERROR(VLOOKUP(B32,Leads!A$3:C$100,3,FALSE),"")) | I32: =IF(H32="","",IFERROR(VLOOKUP(H32,Scripts!A$3:D$60,3,FALSE),"")) | J32: =IF(H32="","",IFERROR(VLOOKUP(H32,Scripts!A$3:D$60,4,FALSE),""))
I33: =IF(H33="","",IFERROR(VLOOKUP(H33,Scripts!A$3:D$60,3,FALSE),"")) | J33: =IF(H33="","",IFERROR(VLOOKUP(H33,Scripts!A$3:D$60,4,FALSE),""))
I34: =IF(H34="","",IFERROR(VLOOKUP(H34,Scripts!A$3:D$60,3,FALSE),"")) | J34: =IF(H34="","",IFERROR(VLOOKUP(H34,Scripts!A$3:D$60,4,FALSE),""))
I35: =IF(H35="","",IFERROR(VLOOKUP(H35,Scripts!A$3:D$60,3,FALSE),"")) | J35: =IF(H35="","",IFERROR(VLOOKUP(H35,Scripts!A$3:D$60,4,FALSE),""))
I36: =IF(H36="","",IFERROR(VLOOKUP(H36,Scripts!A$3:D$60,3,FALSE),"")) | J36: =IF(H36="","",IFERROR(VLOOKUP(H36,Scripts!A$3:D$60,4,FALSE),""))
I37: =IF(H37="","",IFERROR(VLOOKUP(H37,Scripts!A$3:D$60,3,FALSE),"")) | J37: =IF(H37="","",IFERROR(VLOOKUP(H37,Scripts!A$3:D$60,4,FALSE),""))
I38: =IF(H38="","",IFERROR(VLOOKUP(H38,Scripts!A$3:D$60,3,FALSE),"")) | J38: =IF(H38="","",IFERROR(VLOOKUP(H38,Scripts!A$3:D$60,4,FALSE),""))
I39: =IF(H39="","",IFERROR(VLOOKUP(H39,Scripts!A$3:D$60,3,FALSE),"")) | J39: =IF(H39="","",IFERROR(VLOOKUP(H39,Scripts!A$3:D$60,4,FALSE),""))
I40: =IF(H40="","",IFERROR(VLOOKUP(H40,Scripts!A$3:D$60,3,FALSE),"")) | J40: =IF(H40="","",IFERROR(VLOOKUP(H40,Scripts!A$3:D$60,4,FALSE),""))
I41: =IF(H41="","",IFERROR(VLOOKUP(H41,Scripts!A$3:D$60,3,FALSE),"")) | J41: =IF(H41="","",IFERROR(VLOOKUP(H41,Scripts!A$3:D$60,4,FALSE),""))
I42: =IF(H42="","",IFERROR(VLOOKUP(H42,Scripts!A$3:D$60,3,FALSE),"")) | J42: =IF(H42="","",IFERROR(VLOOKUP(H42,Scripts!A$3:D$60,4,FALSE),""))
I43: =IF(H43="","",IFERROR(VLOOKUP(H43,Scripts!A$3:D$60,3,FALSE),"")) | J43: =IF(H43="","",IFERROR(VLOOKUP(H43,Scripts!A$3:D$60,4,FALSE),""))
I44: =IF(H44="","",IFERROR(VLOOKUP(H44,Scripts!A$3:D$60,3,FALSE),"")) | J44: =IF(H44="","",IFERROR(VLOOKUP(H44,Scripts!A$3:D$60,4,FALSE),""))
... I100: =IF(H100="","",IFERROR(VLOOKUP(H100,Scripts!A$3:D$60,3,FALSE),"")) | J100: =IF(H100="","",IFERROR(VLOOKUP(H100,Scripts!A$3:D$60,4,FALSE),""))

Sheet Invoices
A1: Invoices | Q1: =HYPERLINK("#'Cover'!A1","←") -> ←
A2: Invoice No. | B2: Date | C2: Student | D2: Package | E2: Price | F2: Qty | G2: Discount | H2: Total | I2: Paid | J2: Paid date | K2: Script No. | L2: Script CN | M2: Source | N2: Approved by | O2: Script EN | P2: Type
A3: INV-2026-001 | C3: Josh D1 | E3: 400 | F3: 20 | G3: 0 | H3: =IF(E3="","",E3*IF(F3="",0,F3)-IF(G3="",0,G3)) -> 8000 | I3: Paid | K3: P1 | M3: Referral
D4: =IF(C4="","",IFERROR(VLOOKUP(C4,Students!B$3:F$100,5,FALSE),"")) | H4: =IF(E4="","",E4*IF(F4="",0,F4)-IF(G4="",0,G4)) | L4: =IF(K4="","",IFERROR(VLOOKUP(K4,Scripts!A$3:D$60,3,FALSE),"")) | O4: =IF(K4="","",IFERROR(VLOOKUP(K4,Scripts!A$3:D$60,4,FALSE),""))
D5: =IF(C5="","",IFERROR(VLOOKUP(C5,Students!B$3:F$100,5,FALSE),"")) | H5: =IF(E5="","",E5*IF(F5="",0,F5)-IF(G5="",0,G5)) | L5: =IF(K5="","",IFERROR(VLOOKUP(K5,Scripts!A$3:D$60,3,FALSE),"")) | O5: =IF(K5="","",IFERROR(VLOOKUP(K5,Scripts!A$3:D$60,4,FALSE),""))
D6: =IF(C6="","",IFERROR(VLOOKUP(C6,Students!B$3:F$100,5,FALSE),"")) | H6: =IF(E6="","",E6*IF(F6="",0,F6)-IF(G6="",0,G6)) | L6: =IF(K6="","",IFERROR(VLOOKUP(K6,Scripts!A$3:D$60,3,FALSE),"")) | O6: =IF(K6="","",IFERROR(VLOOKUP(K6,Scripts!A$3:D$60,4,FALSE),""))
D7: =IF(C7="","",IFERROR(VLOOKUP(C7,Students!B$3:F$100,5,FALSE),"")) | H7: =IF(E7="","",E7*IF(F7="",0,F7)-IF(G7="",0,G7)) | L7: =IF(K7="","",IFERROR(VLOOKUP(K7,Scripts!A$3:D$60,3,FALSE),"")) | O7: =IF(K7="","",IFERROR(VLOOKUP(K7,Scripts!A$3:D$60,4,FALSE),""))
D8: =IF(C8="","",IFERROR(VLOOKUP(C8,Students!B$3:F$100,5,FALSE),"")) | H8: =IF(E8="","",E8*IF(F8="",0,F8)-IF(G8="",0,G8)) | L8: =IF(K8="","",IFERROR(VLOOKUP(K8,Scripts!A$3:D$60,3,FALSE),"")) | O8: =IF(K8="","",IFERROR(VLOOKUP(K8,Scripts!A$3:D$60,4,FALSE),""))
D9: =IF(C9="","",IFERROR(VLOOKUP(C9,Students!B$3:F$100,5,FALSE),"")) | H9: =IF(E9="","",E9*IF(F9="",0,F9)-IF(G9="",0,G9)) | L9: =IF(K9="","",IFERROR(VLOOKUP(K9,Scripts!A$3:D$60,3,FALSE),"")) | O9: =IF(K9="","",IFERROR(VLOOKUP(K9,Scripts!A$3:D$60,4,FALSE),""))
D10: =IF(C10="","",IFERROR(VLOOKUP(C10,Students!B$3:F$100,5,FALSE),"")) | H10: =IF(E10="","",E10*IF(F10="",0,F10)-IF(G10="",0,G10)) | L10: =IF(K10="","",IFERROR(VLOOKUP(K10,Scripts!A$3:D$60,3,FALSE),"")) | O10: =IF(K10="","",IFERROR(VLOOKUP(K10,Scripts!A$3:D$60,4,FALSE),""))
D11: =IF(C11="","",IFERROR(VLOOKUP(C11,Students!B$3:F$100,5,FALSE),"")) | H11: =IF(E11="","",E11*IF(F11="",0,F11)-IF(G11="",0,G11)) | L11: =IF(K11="","",IFERROR(VLOOKUP(K11,Scripts!A$3:D$60,3,FALSE),"")) | O11: =IF(K11="","",IFERROR(VLOOKUP(K11,Scripts!A$3:D$60,4,FALSE),""))
D12: =IF(C12="","",IFERROR(VLOOKUP(C12,Students!B$3:F$100,5,FALSE),"")) | H12: =IF(E12="","",E12*IF(F12="",0,F12)-IF(G12="",0,G12)) | L12: =IF(K12="","",IFERROR(VLOOKUP(K12,Scripts!A$3:D$60,3,FALSE),"")) | O12: =IF(K12="","",IFERROR(VLOOKUP(K12,Scripts!A$3:D$60,4,FALSE),""))
D13: =IF(C13="","",IFERROR(VLOOKUP(C13,Students!B$3:F$100,5,FALSE),"")) | H13: =IF(E13="","",E13*IF(F13="",0,F13)-IF(G13="",0,G13)) | L13: =IF(K13="","",IFERROR(VLOOKUP(K13,Scripts!A$3:D$60,3,FALSE),"")) | O13: =IF(K13="","",IFERROR(VLOOKUP(K13,Scripts!A$3:D$60,4,FALSE),""))
D14: =IF(C14="","",IFERROR(VLOOKUP(C14,Students!B$3:F$100,5,FALSE),"")) | H14: =IF(E14="","",E14*IF(F14="",0,F14)-IF(G14="",0,G14)) | L14: =IF(K14="","",IFERROR(VLOOKUP(K14,Scripts!A$3:D$60,3,FALSE),"")) | O14: =IF(K14="","",IFERROR(VLOOKUP(K14,Scripts!A$3:D$60,4,FALSE),""))
D15: =IF(C15="","",IFERROR(VLOOKUP(C15,Students!B$3:F$100,5,FALSE),"")) | H15: =IF(E15="","",E15*IF(F15="",0,F15)-IF(G15="",0,G15)) | L15: =IF(K15="","",IFERROR(VLOOKUP(K15,Scripts!A$3:D$60,3,FALSE),"")) | O15: =IF(K15="","",IFERROR(VLOOKUP(K15,Scripts!A$3:D$60,4,FALSE),""))
... D32: =IF(C32="","",IFERROR(VLOOKUP(C32,Students!B$3:F$100,5,FALSE),"")) | H32: =IF(E32="","",E32*IF(F32="",0,F32)-IF(G32="",0,G32)) | L32: =IF(K32="","",IFERROR(VLOOKUP(K32,Scripts!A$3:D$60,3,FALSE),"")) | O32: =IF(K32="","",IFERROR(VLOOKUP(K32,Scripts!A$3:D$60,4,FALSE),""))
L33: =IF(K33="","",IFERROR(VLOOKUP(K33,Scripts!A$3:D$60,3,FALSE),"")) | O33: =IF(K33="","",IFERROR(VLOOKUP(K33,Scripts!A$3:D$60,4,FALSE),""))
G34: TOTAL | H34: =SUM(H3:H32) -> 8000 | L34: =IF(K34="","",IFERROR(VLOOKUP(K34,Scripts!A$3:D$60,3,FALSE),"")) | O34: =IF(K34="","",IFERROR(VLOOKUP(K34,Scripts!A$3:D$60,4,FALSE),""))

Sheet Expenses
A1: Expenses | G1: =HYPERLINK("#'Cover'!A1","←") -> ←
A2: Date | B2: Item | C2: Category | D2: Amount | E2: Note | F2: Approved by
C34: TOTAL | D34: =SUM(D3:D32) -> 0

Sheet Makeup_Churn
A1: Make-ups & At-Risk | H1: =HYPERLINK("#'Cover'!A1","←") -> ←
A2: Student | B2: Absence dates | C2: Absences | D2: Make-up date | E2: Done | F2: Alert | G2: Message
F4: =IF(C4="","",IF(C4>=2,"At risk — talk now",IF(C4>=1,"Watch","OK"))) | G4: =IF(F4="At risk — talk now",IFERROR(VLOOKUP("M2",Scripts!A$3:D$60,3,FALSE),""),IF(F4="Watch",IFERROR(VLOOKUP("M1",Scripts!A$3:D$60,3,FALSE),""),""))
F5: =IF(C5="","",IF(C5>=2,"At risk — talk now",IF(C5>=1,"Watch","OK"))) | G5: =IF(F5="At risk — talk now",IFERROR(VLOOKUP("M2",Scripts!A$3:D$60,3,FALSE),""),IF(F5="Watch",IFERROR(VLOOKUP("M1",Scripts!A$3:D$60,3,FALSE),""),""))
F6: =IF(C6="","",IF(C6>=2,"At risk — talk now",IF(C6>=1,"Watch","OK"))) | G6: =IF(F6="At risk — talk now",IFERROR(VLOOKUP("M2",Scripts!A$3:D$60,3,FALSE),""),IF(F6="Watch",IFERROR(VLOOKUP("M1",Scripts!A$3:D$60,3,FALSE),""),""))
F7: =IF(C7="","",IF(C7>=2,"At risk — talk now",IF(C7>=1,"Watch","OK"))) | G7: =IF(F7="At risk — talk now",IFERROR(VLOOKUP("M2",Scripts!A$3:D$60,3,FALSE),""),IF(F7="Watch",IFERROR(VLOOKUP("M1",Scripts!A$3:D$60,3,FALSE),""),""))
F8: =IF(C8="","",IF(C8>=2,"At risk — talk now",IF(C8>=1,"Watch","OK"))) | G8: =IF(F8="At risk — talk now",IFERROR(VLOOKUP("M2",Scripts!A$3:D$60,3,FALSE),""),IF(F8="Watch",IFERROR(VLOOKUP("M1",Scripts!A$3:D$60,3,FALSE),""),""))
F9: =IF(C9="","",IF(C9>=2,"At risk — talk now",IF(C9>=1,"Watch","OK"))) | G9: =IF(F9="At risk — talk now",IFERROR(VLOOKUP("M2",Scripts!A$3:D$60,3,FALSE),""),IF(F9="Watch",IFERROR(VLOOKUP("M1",Scripts!A$3:D$60,3,FALSE),""),""))
F10: =IF(C10="","",IF(C10>=2,"At risk — talk now",IF(C10>=1,"Watch","OK"))) | G10: =IF(F10="At risk — talk now",IFERROR(VLOOKUP("M2",Scripts!A$3:D$60,3,FALSE),""),IF(F10="Watch",IFERROR(VLOOKUP("M1",Scripts!A$3:D$60,3,FALSE),""),""))
F11: =IF(C11="","",IF(C11>=2,"At risk — talk now",IF(C11>=1,"Watch","OK"))) | G11: =IF(F11="At risk — talk now",IFERROR(VLOOKUP("M2",Scripts!A$3:D$60,3,FALSE),""),IF(F11="Watch",IFERROR(VLOOKUP("M1",Scripts!A$3:D$60,3,FALSE),""),""))
F12: =IF(C12="","",IF(C12>=2,"At risk — talk now",IF(C12>=1,"Watch","OK"))) | G12: =IF(F12="At risk — talk now",IFERROR(VLOOKUP("M2",Scripts!A$3:D$60,3,FALSE),""),IF(F12="Watch",IFERROR(VLOOKUP("M1",Scripts!A$3:D$60,3,FALSE),""),""))
F13: =IF(C13="","",IF(C13>=2,"At risk — talk now",IF(C13>=1,"Watch","OK"))) | G13: =IF(F13="At risk — talk now",IFERROR(VLOOKUP("M2",Scripts!A$3:D$60,3,FALSE),""),IF(F13="Watch",IFERROR(VLOOKUP("M1",Scripts!A$3:D$60,3,FALSE),""),""))
F14: =IF(C14="","",IF(C14>=2,"At risk — talk now",IF(C14>=1,"Watch","OK"))) | G14: =IF(F14="At risk — talk now",IFERROR(VLOOKUP("M2",Scripts!A$3:D$60,3,FALSE),""),IF(F14="Watch",IFERROR(VLOOKUP("M1",Scripts!A$3:D$60,3,FALSE),""),""))
F15: =IF(C15="","",IF(C15>=2,"At risk — talk now",IF(C15>=1,"Watch","OK"))) | G15: =IF(F15="At risk — talk now",IFERROR(VLOOKUP("M2",Scripts!A$3:D$60,3,FALSE),""),IF(F15="Watch",IFERROR(VLOOKUP("M1",Scripts!A$3:D$60,3,FALSE),""),""))
... F32: =IF(C32="","",IF(C32>=2,"At risk — talk now",IF(C32>=1,"Watch","OK"))) | G32: =IF(F32="At risk — talk now",IFERROR(VLOOKUP("M2",Scripts!A$3:D$60,3,FALSE),""),IF(F32="Watch",IFERROR(VLOOKUP("M1",Scripts!A$3:D$60,3,FALSE),""),""))
G33: =IF(F33="At risk — talk now",IFERROR(VLOOKUP("M2",Scripts!A$3:D$60,3,FALSE),""),IF(F33="Watch",IFERROR(VLOOKUP("M1",Scripts!A$3:D$60,3,FALSE),""),""))
G34: =IF(F34="At risk — talk now",IFERROR(VLOOKUP("M2",Scripts!A$3:D$60,3,FALSE),""),IF(F34="Watch",IFERROR(VLOOKUP("M1",Scripts!A$3:D$60,3,FALSE),""),""))
G35: =IF(F35="At risk — talk now",IFERROR(VLOOKUP("M2",Scripts!A$3:D$60,3,FALSE),""),IF(F35="Watch",IFERROR(VLOOKUP("M1",Scripts!A$3:D$60,3,FALSE),""),""))
G36: =IF(F36="At risk — talk now",IFERROR(VLOOKUP("M2",Scripts!A$3:D$60,3,FALSE),""),IF(F36="Watch",IFERROR(VLOOKUP("M1",Scripts!A$3:D$60,3,FALSE),""),""))
G37: =IF(F37="At risk — talk now",IFERROR(VLOOKUP("M2",Scripts!A$3:D$60,3,FALSE),""),IF(F37="Watch",IFERROR(VLOOKUP("M1",Scripts!A$3:D$60,3,FALSE),""),""))
G38: =IF(F38="At risk — talk now",IFERROR(VLOOKUP("M2",Scripts!A$3:D$60,3,FALSE),""),IF(F38="Watch",IFERROR(VLOOKUP("M1",Scripts!A$3:D$60,3,FALSE),""),""))
G39: =IF(F39="At risk — talk now",IFERROR(VLOOKUP("M2",Scripts!A$3:D$60,3,FALSE),""),IF(F39="Watch",IFERROR(VLOOKUP("M1",Scripts!A$3:D$60,3,FALSE),""),""))
G40: =IF(F40="At risk — talk now",IFERROR(VLOOKUP("M2",Scripts!A$3:D$60,3,FALSE),""),IF(F40="Watch",IFERROR(VLOOKUP("M1",Scripts!A$3:D$60,3,FALSE),""),""))
G41: =IF(F41="At risk — talk now",IFERROR(VLOOKUP("M2",Scripts!A$3:D$60,3,FALSE),""),IF(F41="Watch",IFERROR(VLOOKUP("M1",Scripts!A$3:D$60,3,FALSE),""),""))
G42: =IF(F42="At risk — talk now",IFERROR(VLOOKUP("M2",Scripts!A$3:D$60,3,FALSE),""),IF(F42="Watch",IFERROR(VLOOKUP("M1",Scripts!A$3:D$60,3,FALSE),""),""))
G43: =IF(F43="At risk — talk now",IFERROR(VLOOKUP("M2",Scripts!A$3:D$60,3,FALSE),""),IF(F43="Watch",IFERROR(VLOOKUP("M1",Scripts!A$3:D$60,3,FALSE),""),""))
G44: =IF(F44="At risk — talk now",IFERROR(VLOOKUP("M2",Scripts!A$3:D$60,3,FALSE),""),IF(F44="Watch",IFERROR(VLOOKUP("M1",Scripts!A$3:D$60,3,FALSE),""),""))
... G100: =IF(F100="At risk — talk now",IFERROR(VLOOKUP("M2",Scripts!A$3:D$60,3,FALSE),""),IF(F100="Watch",IFERROR(VLOOKUP("M1",Scripts!A$3:D$60,3,FALSE),""),""))

Sheet Events
A1: Events & Materials | H1: =HYPERLINK("#'Cover'!A1","←") -> ←
A2: Event | B2: Item | C2: Qty | D2: Unit price | E2: Subtotal | F2: Owner | G2: Done?
A3: CCA closing gift | C3: 30 | D3: 50 | E3: =IF(C3="","",C3*D3) -> 1500
A4: Halloween | B4: Pumpkin + decor | C4: 2 | D4: 2000 | E4: =IF(C4="","",C4*D4) -> 4000
A5: Winter camp | B5: Poster flyer | C5: 100 | D5: 15 | E5: =IF(C5="","",C5*D5) -> 1500
E6: =IF(C6="","",C6*D6)
E7: =IF(C7="","",C7*D7)
E8: =IF(C8="","",C8*D8)
E9: =IF(C9="","",C9*D9)
E10: =IF(C10="","",C10*D10)
E11: =IF(C11="","",C11*D11)
E12: =IF(C12="","",C12*D12)
E13: =IF(C13="","",C13*D13)
E14: =IF(C14="","",C14*D14)
E15: =IF(C15="","",C15*D15)
E16: =IF(C16="","",C16*D16)
E17: =IF(C17="","",C17*D17)
... E32: =IF(C32="","",C32*D32)

Sheet WinterCamp
A1: Winter Camp | I1: =HYPERLINK("#'Cover'!A1","←") -> ←
A2: Child | B2: School | C2: Week | D2: Returning | E2: Fee | F2: Paid | G2: Fill | H2: Notes
E3: =IF(A3="","",9000)
E4: =IF(A4="","",9000) | G4: =IF(C4="","",IF(COUNTIF(C$3:C$50,C4)>=4,"Full",""&(4-COUNTIF(C$3:C$50,C4))&" kids"))
E5: =IF(A5="","",9000) | G5: =IF(C5="","",IF(COUNTIF(C$3:C$50,C5)>=4,"Full",""&(4-COUNTIF(C$3:C$50,C5))&" kids"))
E6: =IF(A6="","",9000) | G6: =IF(C6="","",IF(COUNTIF(C$3:C$50,C6)>=4,"Full",""&(4-COUNTIF(C$3:C$50,C6))&" kids"))
E7: =IF(A7="","",9000) | G7: =IF(C7="","",IF(COUNTIF(C$3:C$50,C7)>=4,"Full",""&(4-COUNTIF(C$3:C$50,C7))&" kids"))
E8: =IF(A8="","",9000) | G8: =IF(C8="","",IF(COUNTIF(C$3:C$50,C8)>=4,"Full",""&(4-COUNTIF(C$3:C$50,C8))&" kids"))
E9: =IF(A9="","",9000) | G9: =IF(C9="","",IF(COUNTIF(C$3:C$50,C9)>=4,"Full",""&(4-COUNTIF(C$3:C$50,C9))&" kids"))
E10: =IF(A10="","",9000) | G10: =IF(C10="","",IF(COUNTIF(C$3:C$50,C10)>=4,"Full",""&(4-COUNTIF(C$3:C$50,C10))&" kids"))
E11: =IF(A11="","",9000) | G11: =IF(C11="","",IF(COUNTIF(C$3:C$50,C11)>=4,"Full",""&(4-COUNTIF(C$3:C$50,C11))&" kids"))
E12: =IF(A12="","",9000) | G12: =IF(C12="","",IF(COUNTIF(C$3:C$50,C12)>=4,"Full",""&(4-COUNTIF(C$3:C$50,C12))&" kids"))
E13: =IF(A13="","",9000) | G13: =IF(C13="","",IF(COUNTIF(C$3:C$50,C13)>=4,"Full",""&(4-COUNTIF(C$3:C$50,C13))&" kids"))
E14: =IF(A14="","",9000) | G14: =IF(C14="","",IF(COUNTIF(C$3:C$50,C14)>=4,"Full",""&(4-COUNTIF(C$3:C$50,C14))&" kids"))
E15: =IF(A15="","",9000) | G15: =IF(C15="","",IF(COUNTIF(C$3:C$50,C15)>=4,"Full",""&(4-COUNTIF(C$3:C$50,C15))&" kids"))
... E100: =IF(A100="","",9000) | G100: =IF(C100="","",IF(COUNTIF(C$3:C$50,C100)>=4,"Full",""&(4-COUNTIF(C$3:C$50,C100))&" kids"))

Sheet Camp_Plan
A1: Winter Camp Plan | G1: =HYPERLINK("#'Cover'!A1","←") -> ←
A2: Milestone | B2: Item | C2: Owner | D2: Done? | E2: Notes | F2: Script
A4: Dec | B4: W1 Christmas week — dates locked with parents/schools | E4: 3 weeks total per model; Jan counts 3
A5: Dec | B5: W2 New Year week | E5: Goats-in-Art all 3 weeks
A6: Jan | B6: W3 after-New-Year week | E6: Min 4 kids/week to open
A7: Nov | B7: Goat sculpture Proof standing in the studio (kids see it, want it) | E7: Danny designs
A8: Nov | B8: Week split: sculpture ~12h + painting ~8h = 20h (5 days x 6h incl lunch, 2 breaks) | E8: Topic-focused, one theme
A9: Nov | B9: Daily rule: finished work to take home every day
A10: Nov | B10: Fee CNY 9,000/kid/week; list-price story 400/hr; early-bird + royalty discounts only, each in writing | C10: Approvals | E10: Strict pricing; private rates stay private | F10: F1
A11: Early Dec | B11: Ask regulars staying in Shanghai with K1 (soft, chat-first); invite them to refer a friend staying too | E11: No hard sell | F11: K1
A12: Mid Dec | B12: 100 flyers + QR out
A13: 1 wk before | B13: Headcount per week: 4+ open; under 4 merge into the studio group (studio rent CNY 1,000/day line) | E13: Few kids = studio, not school site
A14: 1 wk before | B14: Roles: Teacher + Helper; lunch plan; materials kits in Events
A15: Camp open | B15: Film with V1 consents only (white canvas to finish) | E15: No signed row, no camera | F15: V1
A16: T+1 day | B16: Thank-you + trial/enrolment pack to every camp family; log in Trials/Leads | E16: 24h rule | F16: T1

Sheet Scripts
A1: Messages | E1: =HYPERLINK("#'Cover'!A1","←") -> ←
A2: No. | B2: Scenario | C2: Message (EN) | D2: Message (CN)
A3: P1 | B3: Send invoice | C3: Hello [name], attached is [child]'s fee summary for [dates]: [n] sessions, CNY [amount]. At NovArt every session is planned around your child, so no two classes are the same. Let me know if you'd like anything adjusted. | D3: 您好[称呼]，附件是[孩子][日期]的费用小结：共[n]节，合计[金额]元。在NovArt，每节课都围绕孩子单独设计，不会有两节完全一样的课。如需调整，随时告诉我。
A4: P2 | B4: Gentle nudge | C4: Hello [name], floating last week's fee summary back to the top — it may be buried in a busy inbox. No rush; reply when it suits you and I'll resend the breakdown. | D4: 您好[称呼]，把上周的费用小结再顶一下，可能沉在未读里了。不着急，方便时回我一声，我把明细再发一份。
A5: T1 | B5: Post-trial 24h | C5: It was lovely having [child] today — [one concrete thing they did]. The course plan is attached; confirming this week keeps the same teacher and slot from next week. | D5: 今天[孩子]表现很好，[一件具体的事]。课程方案附后，本周确认的话，下周起是同一位老师、同一个时间，孩子不用重新适应。
A6: T2 | B6: Trial passed | C6: No pressure at all — art can't be rushed. If you have a moment, tell me what held you back (timing, fee, or simply not yet) so I can note it. When a camp or workshop fits, you'll hear from me first. | D6: 完全没关系，艺术急不得。方便的话告诉我一声，是时间、费用，还是时机未到，我记下来。以后有合适的营或工坊，我第一个告诉您。
A7: R1 | B7: Renewal | C7: Heads-up: [child] has 2 sessions left, finishing around [date]. The next block brings a new artist and new techniques, and the teacher already has a direction in mind for [child]. Shall I hold the slot? | D7: 提醒一下，[孩子]还剩2节，大约[日期]结课。下一轮是新的艺术家和新技法，老师已经给[孩子]想好了方向。需要我把名额留住吗？
A8: M1 | B8: Make-up | C8: We missed [child] today — hope all is well. Would Saturday or Sunday work for a make-up? Send me a time and I'll book it with the teacher. | D8: 今天没见到[孩子]，希望一切都好。周六或周日方便补课吗？给我一个时间，我去跟老师约好。
A9: M2 | B9: At-risk check | C9: We haven't seen [child] for two weeks — is the current time still working? Tell me a better slot and I'll move things around. [Child] was just finding their stride; stopping now would be a pity. | D9: 两周没见到[孩子]了，现在的时间还方便吗？告诉我更合适的时间，我来调整。孩子刚找到感觉，这时候停下来挺可惜的。
A10: C1 | B10: CCA to studio | C10: You're warmly invited: our end-of-term mini exhibition opens Saturday afternoon, and [child] has work in it. Come hear them talk it through for five minutes — grandparents very welcome too. Afterwards, come upstairs and see the studio. | D10: 诚挚邀请：结课小展周六下午开幕，[孩子]有作品参展。欢迎来听孩子讲五分钟，祖父母也一起来。展后欢迎上楼参观工作室。
A11: G1 | B11: Referral ask | C11: If friends ever ask about art classes, feel free to pass along our referral card. Every referring family gets a thank-you, arranged privately. Most of our families found us this way. | D11: 如果朋友问起艺术课，欢迎把我们的引荐卡转给他们。每位转介绍的家庭都有心意，私下安排。我们大部分家庭都是这样来的。
A12: V1 | B12: Photo consent | C12: We'd love to include [child]'s best moments in this week's short film, posted only on our official account. Close-ups always need your OK first — the consent form is attached, and a 'no' on any line is fully respected. | D12: 想把[孩子]本周的精彩瞬间放进本周短片，只发官方账号。特写镜头一定先征得您的同意，授权书附后，任何一条写“不同意”，我们都照办。
A13: S1 | B13: Showcase invite | C13: You're invited to our art get-together this Saturday afternoon. Each child presents their work for about five minutes — grandparents warmly welcome. Hope to see you there. | D13: 邀请您参加本周六下午的艺术小聚。每个孩子上台讲五分钟自己的作品，欢迎祖父母一起来。期待见到您。
... A18: U1 | B18: Second nudge (firm) | C18: Hello [name], following up on the [date] summary (CNY [amount]) — still open. If timing is the issue, give me a date and I'll note it. Otherwise please settle this week so [child]'s classes run uninterrupted. | D18: 您好[称呼]，[日期]的费用单（[金额]元）还没结。如果是付款时间的问题，告诉我一个日期，我记下来。不然的话，麻烦本周结一下，孩子上课不受影响。

Sheet Send_Kit
A1: Send Kit | E1: =HYPERLINK("#'Cover'!A1","←") -> ←
A2: Scenario (pick) | B2: Trial invite
A3: 1 Script (copy) | B3: =IF($B$2="","",CHOOSE(MATCH($B$2,{"First touch";"Trial invite";"Post-trial";"Invoice";"Renewal";"CCA convert";"Referral"},0),"C1: Scripts C1 bilingual","T1: Scripts T1","T1 enrolled / T2 passed: Scripts","P1: Scripts P1","R1: Scripts R1","C1: Scripts C1","G1: Scripts G1")) -> T1: Scripts T1
A4: 2 Flyer (SKU) | B4: =IF($B$2="","",CHOOSE(MATCH($B$2,{"First touch";"Trial invite";"Post-trial";"Invoice";"Renewal";"CCA convert";"Referral"},0),"M-01 trial flyer","M-01 trial flyer","M-01 + M-03 booklet","M-03 booklet + invoice no.","M-02 calendar + new invoice","M-01 + M-06 closing gift","M-04 referral card")) -> M-01 trial flyer
A5: 3 Invoice (which) | B5: =IF($B$2="","",CHOOSE(MATCH($B$2,{"First touch";"Trial invite";"Post-trial";"Invoice";"Renewal";"CCA convert";"Referral"},0),"No invoice yet","No invoice yet","Optional","Invoice no. in Invoices","New invoice","No invoice yet","Invoice on sign-up")) -> No invoice yet
A6: 4 Checklist | B6: =IF($B$2="","",CHOOSE(MATCH($B$2,{"First touch";"Trial invite";"Post-trial";"Invoice";"Renewal";"CCA convert";"Referral"},0),"Ask age/school/time/budget","Lock room + teacher + reminder","Follow up in 24h, log reason","Discount signed?","2 sessions left, renew now","Consent signed?","10% explained?")) -> Lock room + teacher + reminder
A7: → Script (auto) | B7: =B5 -> No invoice yet
A8: → Flyer (auto) | B8: =B6 -> Lock room + teacher + reminder

Sheet Programs
A1: Programs | H1: =HYPERLINK("#'Cover'!A1","←") -> ←
A2: Semester | B2: Program / Artist | C2: Technique | D2: Hours | E2: Status | F2: Fee | G2: Notes
A3: 2026 Fall
A4: 2026 Fall | B4: Architecture | C4: Construction | D4: 8 | E4: Running | G4: Boats — kids love it
A5: 2027 Q1 | B5: Goats in Art (New Year) | C5: Sculpture | D5: 12 | E5: Planned | G5: Danny designs
A6: 2027 Q1 | B6: Cyanotype | C6: Photographic print | D6: 8 | E6: Planned | G6: Marita Wai style
A7: 2027 Q2 | B7: Romero Britto | C7: Painting | D7: 8 | E7: Idea | G7: girlish — popular
A8: 2027 Q2 | B8: Giacometti | C8: Sculpture | D8: 8 | E8: Idea | G8: hard — small groups
A33: CONFIDENTIAL — studio property. Never share full roadmap outside. Version dated on each edit. | B33: Last updated: | C33: =TODAY() -> 46309

Sheet Exhibitions
A1: Exhibitions | K1: =HYPERLINK("#'Cover'!A1","←") -> ←
A2: Name | B2: Date | C2: Organizer cut | D2: Kids | E2: Group | F2: Package fee | G2: Costs covered | H2: Status | I2: Agreed cut % | J2: Contract
A3: HK show
A4: Next exhibition | B4: 2027-01 | C4: tbc — ask Beijing lady | E4: Exhibition-only | H4: Plan - Amber bridge

Sheet Certificates
A1: Certificates | G1: =HYPERLINK("#'Cover'!A1","←") -> ←
A2: Student | B2: Program / Artist | C2: Hours | D2: Technique | E2: Issued | F2: Signed
A3: e.g. Daphne | B3: Morandi | C3: 8 | D3: Painting

Sheet Channel_Pivot
A1: Channels and Revenue | I1: =HYPERLINK("#'Cover'!A1","←") -> ←
A2: Source | B2: Leads | C2: Contacting | D2: Trial booked | E2: Enrolled | F2: Parked | G2: Conv. | H2: Revenue ¥
A3: CCA showcase | B3: =COUNTIF(Leads!E3:E100,A3) -> 1 | C3: =COUNTIFS(Leads!E3:E100,A3,Leads!G3:G100,"Contacting") -> 1 | D3: =COUNTIFS(Leads!E3:E100,A3,Leads!G3:G100,"Trial booked") -> 0 | E3: =COUNTIFS(Leads!E3:E100,A3,Leads!G3:G100,"Enrolled") -> 0 | F3: =COUNTIFS(Leads!E3:E100,A3,Leads!G3:G100,"Parked") -> 0 | G3: =IFERROR(E3/B3,0) -> 0 | H3: =SUMIFS(Invoices!H3:H34,Invoices!M3:M34,A3,Invoices!I3:I34,"Paid") -> 0
A4: School event | B4: =COUNTIF(Leads!E3:E100,A4) -> 0 | C4: =COUNTIFS(Leads!E3:E100,A4,Leads!G3:G100,"Contacting") -> 0 | D4: =COUNTIFS(Leads!E3:E100,A4,Leads!G3:G100,"Trial booked") -> 0 | E4: =COUNTIFS(Leads!E3:E100,A4,Leads!G3:G100,"Enrolled") -> 0 | F4: =COUNTIFS(Leads!E3:E100,A4,Leads!G3:G100,"Parked") -> 0 | G4: =IFERROR(E4/B4,0) -> 0 | H4: =SUMIFS(Invoices!H3:H34,Invoices!M3:M34,A4,Invoices!I3:I34,"Paid") -> 0
A5: Referral | B5: =COUNTIF(Leads!E3:E100,A5) -> 1 | C5: =COUNTIFS(Leads!E3:E100,A5,Leads!G3:G100,"Contacting") -> 0 | D5: =COUNTIFS(Leads!E3:E100,A5,Leads!G3:G100,"Trial booked") -> 0 | E5: =COUNTIFS(Leads!E3:E100,A5,Leads!G3:G100,"Enrolled") -> 1 | F5: =COUNTIFS(Leads!E3:E100,A5,Leads!G3:G100,"Parked") -> 0 | G5: =IFERROR(E5/B5,0) -> 1 | H5: =SUMIFS(Invoices!H3:H34,Invoices!M3:M34,A5,Invoices!I3:I34,"Paid") -> 8000
A6: Walk-in | B6: =COUNTIF(Leads!E3:E100,A6) -> 0 | C6: =COUNTIFS(Leads!E3:E100,A6,Leads!G3:G100,"Contacting") -> 0 | D6: =COUNTIFS(Leads!E3:E100,A6,Leads!G3:G100,"Trial booked") -> 0 | E6: =COUNTIFS(Leads!E3:E100,A6,Leads!G3:G100,"Enrolled") -> 0 | F6: =COUNTIFS(Leads!E3:E100,A6,Leads!G3:G100,"Parked") -> 0 | G6: =IFERROR(E6/B6,0) -> 0 | H6: =SUMIFS(Invoices!H3:H34,Invoices!M3:M34,A6,Invoices!I3:I34,"Paid") -> 0
A7: Social | B7: =COUNTIF(Leads!E3:E100,A7) -> 0 | C7: =COUNTIFS(Leads!E3:E100,A7,Leads!G3:G100,"Contacting") -> 0 | D7: =COUNTIFS(Leads!E3:E100,A7,Leads!G3:G100,"Trial booked") -> 0 | E7: =COUNTIFS(Leads!E3:E100,A7,Leads!G3:G100,"Enrolled") -> 0 | F7: =COUNTIFS(Leads!E3:E100,A7,Leads!G3:G100,"Parked") -> 0 | G7: =IFERROR(E7/B7,0) -> 0 | H7: =SUMIFS(Invoices!H3:H34,Invoices!M3:M34,A7,Invoices!I3:I34,"Paid") -> 0
A8: EKA | B8: =COUNTIF(Leads!E3:E100,A8) -> 0 | C8: =COUNTIFS(Leads!E3:E100,A8,Leads!G3:G100,"Contacting") -> 0 | D8: =COUNTIFS(Leads!E3:E100,A8,Leads!G3:G100,"Trial booked") -> 0 | E8: =COUNTIFS(Leads!E3:E100,A8,Leads!G3:G100,"Enrolled") -> 0 | F8: =COUNTIFS(Leads!E3:E100,A8,Leads!G3:G100,"Parked") -> 0 | G8: =IFERROR(E8/B8,0) -> 0 | H8: =SUMIFS(Invoices!H3:H34,Invoices!M3:M34,A8,Invoices!I3:I34,"Paid") -> 0
A9: Partner | B9: =COUNTIF(Leads!E3:E100,A9) -> 0 | C9: =COUNTIFS(Leads!E3:E100,A9,Leads!G3:G100,"Contacting") -> 0 | D9: =COUNTIFS(Leads!E3:E100,A9,Leads!G3:G100,"Trial booked") -> 0 | E9: =COUNTIFS(Leads!E3:E100,A9,Leads!G3:G100,"Enrolled") -> 0 | F9: =COUNTIFS(Leads!E3:E100,A9,Leads!G3:G100,"Parked") -> 0 | G9: =IFERROR(E9/B9,0) -> 0 | H9: =SUMIFS(Invoices!H3:H34,Invoices!M3:M34,A9,Invoices!I3:I34,"Paid") -> 0
A10: Birthday WS | B10: =COUNTIF(Leads!E3:E100,A10) -> 0 | C10: =COUNTIFS(Leads!E3:E100,A10,Leads!G3:G100,"Contacting") -> 0 | D10: =COUNTIFS(Leads!E3:E100,A10,Leads!G3:G100,"Trial booked") -> 0 | E10: =COUNTIFS(Leads!E3:E100,A10,Leads!G3:G100,"Enrolled") -> 0 | F10: =COUNTIFS(Leads!E3:E100,A10,Leads!G3:G100,"Parked") -> 0 | G10: =IFERROR(E10/B10,0) -> 0 | H10: =SUMIFS(Invoices!H3:H34,Invoices!M3:M34,A10,Invoices!I3:I34,"Paid") -> 0
A11: TOTAL | B11: =SUM(B3:B10) -> 2 | C11: =SUM(C3:C10) -> 1 | D11: =SUM(D3:D10) -> 0 | E11: =SUM(E3:E10) -> 1 | F11: =SUM(F3:F10) -> 0 | G11: =IFERROR(E11/B11,0) -> 0.5 | H11: =SUM(H3:H10) -> 8000
A12: Month | B12: Revenue (paid)
A13: 2026-10 | B13: =SUMIFS(Invoices!H3:H34,Invoices!B3:B34,">="&DATE(2026,10,1),Invoices!B3:B34,"<"&DATE(2026,11,1),Invoices!I3:I34,"Paid") -> 0
A14: 2026-11 | B14: =SUMIFS(Invoices!H3:H34,Invoices!B3:B34,">="&DATE(2026,11,1),Invoices!B3:B34,"<"&DATE(2026,12,1),Invoices!I3:I34,"Paid") -> 0
A15: 2026-12 | B15: =SUMIFS(Invoices!H3:H34,Invoices!B3:B34,">="&DATE(2026,12,1),Invoices!B3:B34,"<"&DATE(2027,1,1),Invoices!I3:I34,"Paid") -> 0
A16: 2027-01 | B16: =SUMIFS(Invoices!H3:H34,Invoices!B3:B34,">="&DATE(2027,1,1),Invoices!B3:B34,"<"&DATE(2027,2,1),Invoices!I3:I34,"Paid") -> 0
A17: 2027-02 | B17: =SUMIFS(Invoices!H3:H34,Invoices!B3:B34,">="&DATE(2027,2,1),Invoices!B3:B34,"<"&DATE(2027,3,1),Invoices!I3:I34,"Paid") -> 0
A18: 2027-03 | B18: =SUMIFS(Invoices!H3:H34,Invoices!B3:B34,">="&DATE(2027,3,1),Invoices!B3:B34,"<"&DATE(2027,4,1),Invoices!I3:I34,"Paid") -> 0
A19: 2027-04 | B19: =SUMIFS(Invoices!H3:H34,Invoices!B3:B34,">="&DATE(2027,4,1),Invoices!B3:B34,"<"&DATE(2027,5,1),Invoices!I3:I34,"Paid") -> 0
A20: 2027-05 | B20: =SUMIFS(Invoices!H3:H34,Invoices!B3:B34,">="&DATE(2027,5,1),Invoices!B3:B34,"<"&DATE(2027,6,1),Invoices!I3:I34,"Paid") -> 0
A21: 2027-06 | B21: =SUMIFS(Invoices!H3:H34,Invoices!B3:B34,">="&DATE(2027,6,1),Invoices!B3:B34,"<"&DATE(2027,7,1),Invoices!I3:I34,"Paid") -> 0
A22: 2027-07 | B22: =SUMIFS(Invoices!H3:H34,Invoices!B3:B34,">="&DATE(2027,7,1),Invoices!B3:B34,"<"&DATE(2027,8,1),Invoices!I3:I34,"Paid") -> 0
A23: 2027-08 | B23: =SUMIFS(Invoices!H3:H34,Invoices!B3:B34,">="&DATE(2027,8,1),Invoices!B3:B34,"<"&DATE(2027,9,1),Invoices!I3:I34,"Paid") -> 0
A24: 2027-09 | B24: =SUMIFS(Invoices!H3:H34,Invoices!B3:B34,">="&DATE(2027,9,1),Invoices!B3:B34,"<"&DATE(2027,10,1),Invoices!I3:I34,"Paid") -> 0

Sheet Access
A1: Access Control — who can see and edit | F1: =HYPERLINK("#'Cover'!A1","←") -> ←
A2: Member | B2: Role | C2: Can view | D2: Can edit | E2: Locked
A3: Coordinator (TBD) | B3: Workbook author (TBD) | C3: All | D3: All (incl formulas) | E3: —
A4: Nicole | B4: Partner | C4: View all | D4: Sign approvals, discount cols | E4: Finance formulas, structure
A5: Danny | B5: Founder + teacher | C5: View all | D5: Programs content, sign-offs | E5: Finance, contact details

Sheet Consents
A1: Consents | H1: =HYPERLINK("#'Cover'!A1","←") -> ←
A2: Student | B2: Photo | C2: Video | D2: Close-up | E2: School publish | F2: Signed date | G2: File ref
A3: e.g. Josh D1 | B3: Yes | C3: Yes | D3: Yes | E3: No | F3: 2026-10-20

Sheet Approvals
A1: Approvals | H1: =HYPERLINK("#'Cover'!A1","←") -> ←
A2: Date | B2: Type | C2: Student/Item | D2: Amount/Discount | E2: Requested by | F2: Approved by | G2: Status
A3: 2026-10-20 | B3: Discount (early bird/loyal) | C3: Josh 4 kids | D3: 10% off | G3: Requested
B4: Exhibition cut | C4: Beijing organizer % | D4: TBD — get it in writing before any entry work starts | G4: Requested
B5: Partnership | C5: EKA points linkage + 2h staff taster | D5: Pending EKA reply (spend/park link; taster format TBD) | G5: Requested

Sheet Offboarding
A1: Offboarding - Run the day someone steps back | E1: =HYPERLINK("#'Cover'!A1","←") -> ←
A2: Step | B2: Owner | C2: Done | D2: Date
A3: 1. Change shared-doc password
A4: 2. Remove personal devices
A5: 3. Confirm all rows = official account
A6: 4. Export final backup
A7: 5. Revoke shares except founders

Sheet Assets
A1: Asset Library — what we have and what is missing | J1: =HYPERLINK("#'Cover'!A1","←") -> ←
A2: No. | B2: Item | C2: Version/Date | D2: Location | E2: Stock/Link | F2: Script | G2: Notes | H2: Cloud link | I2: Status
A3: M-01 | B3: Trial flyer | C3: Nicole ver. | D3: Cloud/Assets | E3: / | F3: =IF(F3="","",VLOOKUP(F3,Scripts!A$3:D$20,3,FALSE)) -> 0 | G3: Attach for trial families | H3: See Flyer sheet; link final from cloud | I3: Ready
A4: M-02 | B4: 2027 calendar + year plan | C4: To design | D4: See Calendar sheet | E4: / | F4: =IF(F4="","",VLOOKUP(F4,Scripts!A$3:D$20,3,FALSE)) -> 0 | G4: Closing + welcome gifts | I4: Ready
A5: M-03 | B5: Program booklet | C5: To compress | D5: Cloud/Assets | E5: / | F5: =IF(F5="","",VLOOKUP(F5,Scripts!A$3:D$20,3,FALSE)) -> 0 | G5: PDF too big — compress first
A6: M-04 | B6: Referral card | C6: To print | D6: Front desk | E6: / | F6: =IF(F6="","",VLOOKUP(F6,Scripts!A$3:D$20,3,FALSE)) -> 0 | G6: Parents pass on
A7: M-05 | B7: Consent form | C7: Final | D7: Front desk + cloud | E7: / | F7: =IF(F7="","",VLOOKUP(F7,Scripts!A$3:D$20,3,FALSE)) -> 0 | G7: Sign first
A8: M-06 | B8: Closing gift pack | C8: To stock | D8: Studio | E8: / | F8: =IF(F8="","",VLOOKUP(F8,Scripts!A$3:D$20,3,FALSE)) -> 0 | G8: sketchbook + stickers + QR
A9: M-07 | B9: Birthday WS poster | C9: To make | D9: Cloud/Assets | E9: / | F9: =IF(F9="","",VLOOKUP(F9,Scripts!A$3:D$20,3,FALSE)) -> 0 | G9: 6–8 kids
A10: M-08 | B10: Winter camp flyer | C10: Theme TBD by Danny | D10: Cloud/Assets | E10: / | F10: =IF(F10="","",VLOOKUP(F10,Scripts!A$3:D$20,3,FALSE)) -> 0 | G10: Goat-year theme first
A11: M-09 | B11: Invoice slip | C11: See Invoice_Poster | D11: This sheet | E11: / | F11: =IF(F11="","",VLOOKUP(F11,Scripts!A$3:D$60,3,FALSE)) -> 0 | G11: Attach with bills
A12: M-10 | B12: Consent form | C12: See Consent_Poster | D12: Front desk + sheet | E12: / | F12: =IF(F12="","",VLOOKUP(F12,Scripts!A$3:D$60,3,FALSE)) -> 0 | G12: Sign first
A13: M-11 | B13: Survey | C13: See Survey_Poster | D13: This sheet | E13: / | F13: =IF(F13="","",VLOOKUP(F13,Scripts!A$3:D$60,3,FALSE)) -> 0 | G13: Send before renewal
A14: M-12 | B14: Halloween flyer | C14: EN HD | D14: See Halloween sheet | E14: / | F14: =IF(F14="","",VLOOKUP(F14,Scripts!A$3:D$60,3,FALSE)) -> 0 | G14: 10-kid groups, scan to book | I14: Ready
A15: M-13 | B15: For Fun EN | C15: EN ver. | D15: See ForFun_EN | E15: / | F15: =IF(F15="","",VLOOKUP(F15,Scripts!A$3:D$60,3,FALSE)) -> 0 | G15: Swap original logo before print
A16: M-14 | B16: Closing gifts | C16: Mid-Nov ver. | D16: Studio | E16: / | F16: =IF(F16="","",VLOOKUP(F16,Scripts!A$3:D$60,3,FALSE)) -> 0 | G16: sketchbook + stickers + pen + QR + red packet
A17: M-15 | B17: Real pumpkins + carving tools | C17: Halloween | D17: Studio | E17: / | F17: =IF(F17="","",VLOOKUP(F17,Scripts!A$3:D$60,3,FALSE)) -> 0 | G17: Buy early

Sheet Brand
A1: Brand Assets — logo, sign-offs, letterhead | D1: =HYPERLINK("#'Cover'!A1","←") -> ←
A2: Item | B2: Standard / Text | C2: Status
A3: Logo | B3: NovArt STUDIO (Λ-A · mirrored-R · F-T); print body always NOVART, art variants for graphics only | C3: TBD
A4: Email sign-off | B4: TBD | Novart Studio · EKA Tianwu, Pudong; Course enquiries | Email TBD | C4: TBD
A5: WeChat sign-off | B5: TBD | Novart Studio; Official account, reply within 1 hour | C5: TBD
A6: Letterhead | B6: NovArt STUDIO (Λ-A · mirrored-R · F-T); print body always NOVART, art variants for graphics only | C6: To design
A7: Business card | B7: Name + official account + Room 409 EKA Tianwu | C7: To print
A8: Receiving account | B8: Corporate account TBD (never use personal accounts) | C8: TBD

Sheet PDF_List
A1: PDF Build List — list first, design later | G1: =HYPERLINK("#'Cover'!A1","←") -> ←
A2: No. | B2: PDF | C2: Use | D2: Source sheet | E2: Status | F2: Notes
A3: PDF-01 | B3: Invoice slip | C3: Bill parents | D3: Invoices | E3: To design | F3: After logo final
A4: PDF-02 | B4: Consent form | C4: Sign first | D4: Consents | E4: To design | F4: One page per child
A5: PDF-03 | B5: Survey | C5: Send before renewal | D5: Certificates | E5: To design | F5: 1–5 scale
A6: PDF-04 | B6: Program booklet | C6: Send to prospects | D6: Programs | E6: To compress | F6: Source PDF too big
A7: PDF-05 | B7: 2027 calendar | C7: Closing + welcome gifts | D7: Calendar | E7: Draft ready | F7: Nicole ver. filed
A8: PDF-06 | B8: Trial flyer | C8: Send to new leads | D8: Leads | E8: Ready | F8: Nicole ver. filed
A9: PDF-07 | B9: Referral card | C9: Referrals | D9: Students | E9: To design | F9: Print 10% rule
A10: PDF-08 | B10: Completion certificate | C10: Renewal hook | D10: Certificates | E10: To design | F10: Signed by Danny

Sheet Calendar
A1: Class Calendar | B1: =HYPERLINK("#'Cover'!A1","←") -> ←

Sheet Halloween
A1: Halloween Flyer | B1: =HYPERLINK("#'Cover'!A1","←") -> ←

Sheet ForFun_EN
A1: ForFun EN | B1: =HYPERLINK("#'Cover'!A1","←") -> ←

Sheet Flyer
A1: Trial Flyer | B1: =HYPERLINK("#'Cover'!A1","←") -> ←

Sheet Tasklist
A1: Tasks | L1: =HYPERLINK("#'Cover'!A1","←") -> ←
A2: Type | B2: Scope | C2: When | D2: Start | E2: End | F2: Hours | G2: Owner | H2: Check A | I2: Check B | J2: Priority | K2: Done%
A3: Mid Nov | B3: Stock closing gifts (sketchbook + stickers + pen + QR + red packet) | C3: Mid Nov | D3: 2026-11 | E3: 2026-11 | F3: 6h | I3: TBD | J3: P0 | K3: 0
A4: Oct | B4: Window + lift ads live in 3 days | C4: This week | D4: 2026-10 | E4: 2026-10 | F4: 1h | H4: TBD | I4: TBD | J4: P0 | K4: 0
A5: Oct | B5: Buy real pumpkins early + count tables | C5: Before Halloween | D5: 2026-10 | E5: 2026-10 | F5: 2h | H5: TBD | I5: TBD | J5: P0 | K5: 0
A6: Monthly | B6: Collect reviews + referrals | C6: Monthly | D6: 2026-11 | E6: 2027-08 | F6: 2h | H6: TBD | I6: TBD | J6: P0 | K6: 0
A7: P0 | B7: UN to NovArt brand cutover: EKA signage, lift ads, parent notice (old name UN Studio) | C7: This week | D7: 2026-10 | E7: 2026-10 | F7: 2h | H7: TBD | I7: TBD | J7: P0 | K7: 0
A8: Cash | B8: Collect Josh 4-kid fees (discount signed, 24h) | C8: Once | D8: 2026-10 | E8: 2026-10 | F8: 4h | H8: TBD | I8: TBD | J8: P0 | K8: 0
A9: Cash | B9: Revive Daphne-type dormant credits (18-class sleepers) | C9: Once | D9: 2026-10 | E9: 2026-10 | F9: 4h | H9: TBD | I9: TBD | J9: P0 | K9: 0
A10: Cash | B10: Clear unpaid list before each camp/term | C10: Each term | D10: 2026-10 | E10: 2027-08 | F10: 2h | I10: TBD | J10: P0 | K10: 0
A11: Sales | B11: Lock 3 open issues before start: CCA TA, trial fee, credit expiry | C11: Once | D11: 2026-10 | E11: 2026-10 | F11: 3h | I11: TBD | J11: P0 | K11: 0
A12: Sales | B12: Lock 400 list price story in T1 (tailor-made defense) | C12: Once | D12: 2026-10 | E12: 2026-10 | F12: 2h | H12: TBD | I12: TBD | J12: P0 | K12: 0
A13: Expansion | B13: New-school CCA (Wellington/Concordia) | C13: 2027 | D13: 2027-01 | E13: 2027-03 | F13: 4h | I13: TBD | J13: P1 | K13: 0
A14: Phase 1-2 wks | B14: Open public email + social accounts + print consent forms | C14: Once | D14: 2026-10 | E14: 2026-10 | F14: 4h | H14: TBD | I14: TBD | J14: P1 | K14: 0
A15: Phase 7-8 wks | B15: Proof calendar booklet + 2027 Q1 plan | C15: Once | D15: 2026-10 | E15: 2026-10 | F15: 8h | H15: TBD | I15: TBD | J15: P1 | K15: 0
A16: Weekly | B16: 1–2 short videos (shoot/edit/post) | C16: Weekly | D16: 2026-10 | E16: 2027-08 | F16: 4h/wk | H16: TBD | I16: TBD | J16: P1 | K16: 0
A17: EKA liaison | B17: EKA points integration (spend/park) | C17: Nov | D17: 2026-11 | E17: 2026-11 | F17: 4h | H17: TBD | I17: TBD | J17: P1 | K17: 0
A18: Exhibitions | B18: Jan show entry + Beijing cut agreed | C18: Jan | D18: 2027-01 | E18: 2027-01 | F18: 4h | H18: TBD | I18: TBD | J18: P1 | K18: 0
A19: Teaching | B19: 5 programs × 8h per term + rebook scripts | C19: Per term | D19: 2027-03 | E19: 2027-06 | F19: 4h | H19: TBD | I19: TBD | J19: P1 | K19: 0
A20: Certificates | B20: Year-1 group + solo shows + certificates | C20: May–Jun | D20: 2027-05 | E20: 2027-06 | F20: 8h | H20: TBD | I20: TBD | J20: P1 | K20: 0
A21: Weekly | B21: Onboarding: schedule + kit + rules + expectations | C21: Weekly | D21: 2026-10 | E21: 2027-08 | F21: 1h | H21: TBD | I21: TBD | J21: P1 | K21: 0
A22: Weekly | B22: Trial end-to-end: welcome + brief + experience | C22: Weekly | D22: 2026-10 | E22: 2027-08 | F22: 2h | H22: TBD | I22: TBD | J22: P1 | K22: 0
A23: Weekly | B23: Referral upkeep: families + partners + schools | C23: Weekly | D23: 2026-10 | E23: 2027-08 | F23: 1h | H23: TBD | I23: TBD | J23: P1 | K23: 0
A24: Weekly | B24: Campaign calendar + flyers + social content | C24: Weekly | D24: 2026-10 | E24: 2027-08 | F24: 3h | H24: TBD | I24: TBD | J24: P1 | K24: 0
A25: P1 | B25: Audit YIQI ART WeChat account: followers, history posts, migrate/rename plan | C25: Nov | D25: 2026-11 | E25: 2026-11 | F25: 3h | J25: P1 | K25: 0
A26: P1 | B26: Catalog PDF slim-down (too big to send) + 2027 calendar inside | C26: Nov | D26: 2026-11 | E26: 2026-11 | F26: 6h | J26: P1 | K26: 0
A27: P1 | B27: Copycat file: Shun Space evidence screenshots archived (defense only) | C27: Once | D27: 2026-11 | E27: 2026-11 | F27: 2h | J27: P1 | K27: 0
A28: P1 | B28: Exhibition pipeline lock: Beijing lady cut %, Amber bridge, Jan show | C28: Jan | D28: 2027-01 | E28: 2027-01 | F28: 4h | I28: TBD | J28: P1 | K28: 0
A29: P1 | B29: Per-artist one-pager: essence + technique + hours (Danny dictates, you format) | C29: Per term | D29: 2027-03 | E29: 2027-06 | F29: 4h | I29: TBD | J29: P1 | K29: 0
A30: Ops | B30: Weekly showcase clips: white canvas to finish + family photo | C30: Weekly | D30: 2026-11 | E30: 2027-08 | F30: 2h/wk | I30: TBD | J30: P1 | K30: 0
A31: Program | B31: 3-year artist roadmap: 200 artists split by term (retention story) | C31: Once | D31: 2026-11 | E31: 2026-12 | F31: 6h | I31: TBD | J31: P1 | K31: 0
A32: Sales | B32: BirthdayWS packages: 6-8 kids, cost-covering, all guests to trials | C32: Per event | D32: 2026-10 | E32: 2027-08 | F32: 2h/session | I32: TBD | J32: P1 | K32: 0
A33: Review | B33: August lesson ritual: lock summer people + money (lost ¥50k) | C33: Each Aug | D33: 2027-08 | E33: 2027-08 | F33: 2h | I33: TBD | J33: P1 | K33: 0
A34: Weekly | B34: Lead + 24h trial follow-up (Wed/Thu eves) | C34: Weekly | D34: 2026-10 | E34: 2027-08 | F34: 4h/wk | H34: TBD | I34: TBD | J34: P2 | K34: 0
A35: Weekly | B35: Attendance/credits/make-ups/churn (Fri) | C35: Weekly | D35: 2026-10 | E35: 2027-08 | F35: 2h/wk | H35: TBD | I35: TBD | J35: P2 | K35: 0
A36: Weekends | B36: Studio TA + reception + filming | C36: Every weekend | D36: 2026-10 | E36: 2027-08 | F36: 8h | I36: TBD | J36: P2 | K36: 0
A37: EKA liaison | B37: Venue + staff taster (2h free) | C37: As needed | D37: 2026-10 | E37: 2027-08 | F37: 2h/session | I37: TBD | J37: P2 | K37: 0
A38: EKA liaison | B38: EKA staff 2h free taster (Kyiv scarf-machine style: simple + fun, format TBD) | C38: As needed | D38: 2026-10 | E38: 2027-08 | F38: 2h/session | H38: TBD | I38: TBD | J38: P2 | K38: 0
A39: New: adults | B39: Adult tasters (materials/venue separate) | C39: TBD | D39: 2027-08 | E39: 2027-08 | F39: 3h/session | H39: TBD | I39: TBD | J39: P2 | K39: 0
A40: New: props | B40: Studio decor (water feature size TBD — passing thought, lowest priority) | C40: End Oct | D40: 2026-10 | E40: 2026-10 | F40: 2h | H40: TBD | I40: TBD | J40: P2 | K40: 0
A41: Nov | B41: Xmas camp theme goats-in-art + goat sculpture proof | C41: Nov | D41: 2026-11 | E41: 2026-11 | F41: Danny leads | H41: TBD | I41: TBD | J41: P2 | K41: 0
A42: Dec | B42: Lock Xmas 12/24–1/7 + 6-wk summer plan | C42: Dec | D42: 2026-12 | E42: 2026-12 | F42: 2h | I42: TBD | J42: P2 | K42: 0
A43: Wrap-up | B43: [Aug lesson] lock summer people + money early (lost 2 deals ¥50k this Aug) | C43: Each Aug | D43: 2027-08 | E43: 2027-08 | F43: 2h | I43: TBD | J43: P2 | K43: 0
A44: Monthly | B44: Monthly parent updates: progress + feedback + preview | C44: Monthly | D44: 2026-11 | E44: 2027-08 | F44: 2h | H44: TBD | I44: TBD | J44: P2 | K44: 0
A45: Anytime | B45: Complaints/refunds + escalation (with Approvals) | C45: Anytime | D45: 2026-11 | E45: 2027-08 | F45: 1h/event | H45: TBD | I45: TBD | J45: P2 | K45: 0
A46: Weekly | B46: Log no-enrol reasons + revisit | C46: Weekly | D46: 2026-10 | E46: 2027-08 | F46: 1h | I46: TBD | J46: P2 | K46: 0
A47: Per term | B47: Term timetable + rooms/teachers | C47: Per term | D47: 2027-03 | E47: 2027-06 | F47: 4h | I47: TBD | J47: P2 | K47: 0
A48: Metrics weekly | B48: Review 3 rates: trial 60% / enrol 50% / renew TBD + pipeline hygiene | C48: Weekly | D48: 2026-10 | E48: 2027-08 | F48: 1h | I48: TBD | J48: P2 | K48: 0
A49: Ops | B49: Prop trolley for acrylics (functional, not furniture-heavy) | C49: Once | D49: 2026-10 | E49: 2026-10 | F49: 2h | I49: TBD | J49: P2 | K49: 0
A50: Policy each Jun | B50: Summer rota (who collects when Danny away) | C50: Each Jun | D50: 2027-06 | E50: 2027-06 | F50: 2h | I50: TBD | J50: P0 | K50: 0
A51: Policy each Jul | B51: 1 wk before summer: clear unpaid list | C51: Each Jul | D51: 2027-07 | E51: 2027-07 | F51: 4h | I51: TBD | J51: P2 | K51: 0
A52: Open issue | B52: CCA TA: JD says in-school, meeting says no (lock before start) | C52: — | D52: 2027-07 | E52: 2027-07 | F52: 2h | H52: TBD | I52: TBD | J52: P2 | K52: 0
A53: Open issue | B53: Trial fee or free: JD silent, meeting split (lock before start) | C53: — | D53: 2027-07 | E53: 2027-07 | F53: 1h | I53: TBD | J53: P0 | K53: 0
A54: Open issue | B54: Credits expire? Danny relaxed, Nicole wants rebook (write into contract) | C54: — | D54: 2026-10 | E54: 2027-08 | F54: 1h | I54: TBD | J54: P2 | K54: 0
A55: Weekly | B55: Regular weeks (~18h/wk) | C55: Weekly | D55: 2026-10 | E55: 2027-08 | F55: — | I55: TBD | J55: P0 | K55: 0
A56: Finance | B56: Social/commission 10%/hospitality 3% owner + caps (TBD) | C56: — | D56: 2026-10 | E56: 2027-08 | F56: 1h | I56: TBD | J56: P0 | K56: 0
A57: Sales | B57: BirthdayWS packages: 6-8 kids, cost-covering, all guests to trials | C57: Per event | J57: P1 | K57: 0
A58: Review | B58: August lesson ritual: lock summer people + money (lost ¥50k) | C58: Each Aug | D58: 2027-08 | E58: 2027-08 | F58: 2h | J58: P1 | K58: 0
A59: Social | B59: Kick off Rednote: rename to studio, 3 first posts (showcase + camp + goat Proof) | C59: Nov | D59: 2026-11 | E59: 2026-11 | F59: 4h | J59: P1 | K59: 1
A60: Program | B60: Holiday museum-visit format: pick date + linked artist + sign-up sheet (20 signed last time) | C60: Per holiday | D60: 2026-12 | E60: 2027-01 | F60: 3h | J60: P2 | K60: 2

Sheet Invoice_Poster
A1: Invoice Poster | B1: =HYPERLINK("#'Cover'!A1","←") -> ←

Sheet Consent_Poster
A1: Consent Poster | B1: =HYPERLINK("#'Cover'!A1","←") -> ←

Sheet Survey_Poster
A1: Survey Poster | B1: =HYPERLINK("#'Cover'!A1","←") -> ←

Sheet Gantt
A1: =_xlfn.CONCAT("Timeline · ",COUNTIF(U3:U100,"Overdue")," OVERDUE · ",COUNTIF(D3:D100,1)," DONE") -> Timeline · 0 OVERDUE · 0 DONE | V1: =HYPERLINK("#'Cover'!A1","←") -> ←
A2: Task | B2: Start | C2: End | D2: Progress | E2: 2026-10 | F2: 2026-11 | G2: 2026-12 | H2: 2027-01 | I2: 2027-02 | J2: 2027-03 | K2: 2027-04 | L2: 2027-05 | M2: 2027-06 | N2: 2027-07 | O2: 2027-08 | P2: 2027-09 | Q2: 2027-10 | R2: 2027-11 | S2: 2027-12 | T2: Status | U2: Alert
A3: =Tasklist!B3 -> Stock closing gifts (sketchbook + stickers + pen + QR + red packet) | B3: =Tasklist!D3 -> 2026-11 | C3: =Tasklist!E3 -> 2026-11 | D3: =Tasklist!K3 -> 0 | E3: =IF(AND(E$2>=$B3,E$2<=$C3),"X","") | F3: =IF(AND(F$2>=$B3,F$2<=$C3),"X","") -> X | G3: =IF(AND(G$2>=$B3,G$2<=$C3),"X","") | H3: =IF(AND(H$2>=$B3,H$2<=$C3),"X","") | I3: =IF(AND(I$2>=$B3,I$2<=$C3),"X","") | J3: =IF(AND(J$2>=$B3,J$2<=$C3),"X","") | K3: =IF(AND(K$2>=$B3,K$2<=$C3),"X","") | L3: =IF(AND(L$2>=$B3,L$2<=$C3),"X","") | ... S3: =IF(AND(S$2>=$B3,S$2<=$C3),"X","") | T3: =IF(D3>=1,"Done",IF(D3>0,"In progress","Not started")) -> Not started | U3: =IF(D3>=1,"-",IF(C3<TEXT(TODAY(),"yyyy-mm"),"Overdue",IF(B3<=TEXT(TODAY(),"yyyy-mm"),"This month","Not yet"))) -> Not yet
A4: =Tasklist!B4 -> Window + lift ads live in 3 days | B4: =Tasklist!D4 -> 2026-10 | C4: =Tasklist!E4 -> 2026-10 | D4: =Tasklist!K4 -> 0 | E4: =IF(AND(E$2>=$B4,E$2<=$C4),"X","") -> X | F4: =IF(AND(F$2>=$B4,F$2<=$C4),"X","") | G4: =IF(AND(G$2>=$B4,G$2<=$C4),"X","") | H4: =IF(AND(H$2>=$B4,H$2<=$C4),"X","") | I4: =IF(AND(I$2>=$B4,I$2<=$C4),"X","") | J4: =IF(AND(J$2>=$B4,J$2<=$C4),"X","") | K4: =IF(AND(K$2>=$B4,K$2<=$C4),"X","") | L4: =IF(AND(L$2>=$B4,L$2<=$C4),"X","") | ... S4: =IF(AND(S$2>=$B4,S$2<=$C4),"X","") | T4: =IF(D4>=1,"Done",IF(D4>0,"In progress","Not started")) -> Not started | U4: =IF(D4>=1,"-",IF(C4<TEXT(TODAY(),"yyyy-mm"),"Overdue",IF(B4<=TEXT(TODAY(),"yyyy-mm"),"This month","Not yet"))) -> This month
A5: =Tasklist!B5 -> Buy real pumpkins early + count tables | B5: =Tasklist!D5 -> 2026-10 | C5: =Tasklist!E5 -> 2026-10 | D5: =Tasklist!K5 -> 0 | E5: =IF(AND(E$2>=$B5,E$2<=$C5),"X","") -> X | F5: =IF(AND(F$2>=$B5,F$2<=$C5),"X","") | G5: =IF(AND(G$2>=$B5,G$2<=$C5),"X","") | H5: =IF(AND(H$2>=$B5,H$2<=$C5),"X","") | I5: =IF(AND(I$2>=$B5,I$2<=$C5),"X","") | J5: =IF(AND(J$2>=$B5,J$2<=$C5),"X","") | K5: =IF(AND(K$2>=$B5,K$2<=$C5),"X","") | L5: =IF(AND(L$2>=$B5,L$2<=$C5),"X","") | ... S5: =IF(AND(S$2>=$B5,S$2<=$C5),"X","") | T5: =IF(D5>=1,"Done",IF(D5>0,"In progress","Not started")) -> Not started | U5: =IF(D5>=1,"-",IF(C5<TEXT(TODAY(),"yyyy-mm"),"Overdue",IF(B5<=TEXT(TODAY(),"yyyy-mm"),"This month","Not yet"))) -> This month
A6: =Tasklist!B6 -> Collect reviews + referrals | B6: =Tasklist!D6 -> 2026-11 | C6: =Tasklist!E6 -> 2027-08 | D6: =Tasklist!K6 -> 0 | E6: =IF(AND(E$2>=$B6,E$2<=$C6),"X","") | F6: =IF(AND(F$2>=$B6,F$2<=$C6),"X","") -> X | G6: =IF(AND(G$2>=$B6,G$2<=$C6),"X","") -> X | H6: =IF(AND(H$2>=$B6,H$2<=$C6),"X","") -> X | I6: =IF(AND(I$2>=$B6,I$2<=$C6),"X","") -> X | J6: =IF(AND(J$2>=$B6,J$2<=$C6),"X","") -> X | K6: =IF(AND(K$2>=$B6,K$2<=$C6),"X","") -> X | L6: =IF(AND(L$2>=$B6,L$2<=$C6),"X","") -> X | ... S6: =IF(AND(S$2>=$B6,S$2<=$C6),"X","") | T6: =IF(D6>=1,"Done",IF(D6>0,"In progress","Not started")) -> Not started | U6: =IF(D6>=1,"-",IF(C6<TEXT(TODAY(),"yyyy-mm"),"Overdue",IF(B6<=TEXT(TODAY(),"yyyy-mm"),"This month","Not yet"))) -> Not yet
A7: =Tasklist!B7 -> UN to NovArt brand cutover: EKA signage, lift ads, parent notice (old name UN Studio) | B7: =Tasklist!D7 -> 2026-10 | C7: =Tasklist!E7 -> 2026-10 | D7: =Tasklist!K7 -> 0 | E7: =IF(AND(E$2>=$B7,E$2<=$C7),"X","") -> X | F7: =IF(AND(F$2>=$B7,F$2<=$C7),"X","") | G7: =IF(AND(G$2>=$B7,G$2<=$C7),"X","") | H7: =IF(AND(H$2>=$B7,H$2<=$C7),"X","") | I7: =IF(AND(I$2>=$B7,I$2<=$C7),"X","") | J7: =IF(AND(J$2>=$B7,J$2<=$C7),"X","") | K7: =IF(AND(K$2>=$B7,K$2<=$C7),"X","") | L7: =IF(AND(L$2>=$B7,L$2<=$C7),"X","") | ... S7: =IF(AND(S$2>=$B7,S$2<=$C7),"X","") | T7: =IF(D7>=1,"Done",IF(D7>0,"In progress","Not started")) -> Not started | U7: =IF(D7>=1,"-",IF(C7<TEXT(TODAY(),"yyyy-mm"),"Overdue",IF(B7<=TEXT(TODAY(),"yyyy-mm"),"This month","Not yet"))) -> This month
A8: =Tasklist!B8 -> Collect Josh 4-kid fees (discount signed, 24h) | B8: =Tasklist!D8 -> 2026-10 | C8: =Tasklist!E8 -> 2026-10 | D8: =Tasklist!K8 -> 0 | E8: =IF(AND(E$2>=$B8,E$2<=$C8),"X","") -> X | F8: =IF(AND(F$2>=$B8,F$2<=$C8),"X","") | G8: =IF(AND(G$2>=$B8,G$2<=$C8),"X","") | H8: =IF(AND(H$2>=$B8,H$2<=$C8),"X","") | I8: =IF(AND(I$2>=$B8,I$2<=$C8),"X","") | J8: =IF(AND(J$2>=$B8,J$2<=$C8),"X","") | K8: =IF(AND(K$2>=$B8,K$2<=$C8),"X","") | L8: =IF(AND(L$2>=$B8,L$2<=$C8),"X","") | ... S8: =IF(AND(S$2>=$B8,S$2<=$C8),"X","") | T8: =IF(D8>=1,"Done",IF(D8>0,"In progress","Not started")) -> Not started | U8: =IF(D8>=1,"-",IF(C8<TEXT(TODAY(),"yyyy-mm"),"Overdue",IF(B8<=TEXT(TODAY(),"yyyy-mm"),"This month","Not yet"))) -> This month
A9: =Tasklist!B9 -> Revive Daphne-type dormant credits (18-class sleepers) | B9: =Tasklist!D9 -> 2026-10 | C9: =Tasklist!E9 -> 2026-10 | D9: =Tasklist!K9 -> 0 | E9: =IF(AND(E$2>=$B9,E$2<=$C9),"X","") -> X | F9: =IF(AND(F$2>=$B9,F$2<=$C9),"X","") | G9: =IF(AND(G$2>=$B9,G$2<=$C9),"X","") | H9: =IF(AND(H$2>=$B9,H$2<=$C9),"X","") | I9: =IF(AND(I$2>=$B9,I$2<=$C9),"X","") | J9: =IF(AND(J$2>=$B9,J$2<=$C9),"X","") | K9: =IF(AND(K$2>=$B9,K$2<=$C9),"X","") | L9: =IF(AND(L$2>=$B9,L$2<=$C9),"X","") | ... S9: =IF(AND(S$2>=$B9,S$2<=$C9),"X","") | T9: =IF(D9>=1,"Done",IF(D9>0,"In progress","Not started")) -> Not started | U9: =IF(D9>=1,"-",IF(C9<TEXT(TODAY(),"yyyy-mm"),"Overdue",IF(B9<=TEXT(TODAY(),"yyyy-mm"),"This month","Not yet"))) -> This month
A10: =Tasklist!B10 -> Clear unpaid list before each camp/term | B10: =Tasklist!D10 -> 2026-10 | C10: =Tasklist!E10 -> 2027-08 | D10: =Tasklist!K10 -> 0 | E10: =IF(AND(E$2>=$B10,E$2<=$C10),"X","") -> X | F10: =IF(AND(F$2>=$B10,F$2<=$C10),"X","") -> X | G10: =IF(AND(G$2>=$B10,G$2<=$C10),"X","") -> X | H10: =IF(AND(H$2>=$B10,H$2<=$C10),"X","") -> X | I10: =IF(AND(I$2>=$B10,I$2<=$C10),"X","") -> X | J10: =IF(AND(J$2>=$B10,J$2<=$C10),"X","") -> X | K10: =IF(AND(K$2>=$B10,K$2<=$C10),"X","") -> X | L10: =IF(AND(L$2>=$B10,L$2<=$C10),"X","") -> X | ... S10: =IF(AND(S$2>=$B10,S$2<=$C10),"X","") | T10: =IF(D10>=1,"Done",IF(D10>0,"In progress","Not started")) -> Not started | U10: =IF(D10>=1,"-",IF(C10<TEXT(TODAY(),"yyyy-mm"),"Overdue",IF(B10<=TEXT(TODAY(),"yyyy-mm"),"This month","Not yet"))) -> This month
A11: =Tasklist!B11 -> Lock 3 open issues before start: CCA TA, trial fee, credit expiry | B11: =Tasklist!D11 -> 2026-10 | C11: =Tasklist!E11 -> 2026-10 | D11: =Tasklist!K11 -> 0 | E11: =IF(AND(E$2>=$B11,E$2<=$C11),"X","") -> X | F11: =IF(AND(F$2>=$B11,F$2<=$C11),"X","") | G11: =IF(AND(G$2>=$B11,G$2<=$C11),"X","") | H11: =IF(AND(H$2>=$B11,H$2<=$C11),"X","") | I11: =IF(AND(I$2>=$B11,I$2<=$C11),"X","") | J11: =IF(AND(J$2>=$B11,J$2<=$C11),"X","") | K11: =IF(AND(K$2>=$B11,K$2<=$C11),"X","") | L11: =IF(AND(L$2>=$B11,L$2<=$C11),"X","") | ... S11: =IF(AND(S$2>=$B11,S$2<=$C11),"X","") | T11: =IF(D11>=1,"Done",IF(D11>0,"In progress","Not started")) -> Not started | U11: =IF(D11>=1,"-",IF(C11<TEXT(TODAY(),"yyyy-mm"),"Overdue",IF(B11<=TEXT(TODAY(),"yyyy-mm"),"This month","Not yet"))) -> This month
A12: =Tasklist!B12 -> Lock 400 list price story in T1 (tailor-made defense) | B12: =Tasklist!D12 -> 2026-10 | C12: =Tasklist!E12 -> 2026-10 | D12: =Tasklist!K12 -> 0 | E12: =IF(AND(E$2>=$B12,E$2<=$C12),"X","") -> X | F12: =IF(AND(F$2>=$B12,F$2<=$C12),"X","") | G12: =IF(AND(G$2>=$B12,G$2<=$C12),"X","") | H12: =IF(AND(H$2>=$B12,H$2<=$C12),"X","") | I12: =IF(AND(I$2>=$B12,I$2<=$C12),"X","") | J12: =IF(AND(J$2>=$B12,J$2<=$C12),"X","") | K12: =IF(AND(K$2>=$B12,K$2<=$C12),"X","") | L12: =IF(AND(L$2>=$B12,L$2<=$C12),"X","") | ... S12: =IF(AND(S$2>=$B12,S$2<=$C12),"X","") | T12: =IF(D12>=1,"Done",IF(D12>0,"In progress","Not started")) -> Not started | U12: =IF(D12>=1,"-",IF(C12<TEXT(TODAY(),"yyyy-mm"),"Overdue",IF(B12<=TEXT(TODAY(),"yyyy-mm"),"This month","Not yet"))) -> This month
A13: =Tasklist!B50 -> Summer rota (who collects when Danny away) | B13: =Tasklist!D50 -> 2027-06 | C13: =Tasklist!E50 -> 2027-06 | D13: =Tasklist!K50 -> 0 | E13: =IF(AND(E$2>=$B13,E$2<=$C13),"X","") | F13: =IF(AND(F$2>=$B13,F$2<=$C13),"X","") | G13: =IF(AND(G$2>=$B13,G$2<=$C13),"X","") | H13: =IF(AND(H$2>=$B13,H$2<=$C13),"X","") | I13: =IF(AND(I$2>=$B13,I$2<=$C13),"X","") | J13: =IF(AND(J$2>=$B13,J$2<=$C13),"X","") | K13: =IF(AND(K$2>=$B13,K$2<=$C13),"X","") | L13: =IF(AND(L$2>=$B13,L$2<=$C13),"X","") | ... S13: =IF(AND(S$2>=$B13,S$2<=$C13),"X","") | T13: =IF(D13>=1,"Done",IF(D13>0,"In progress","Not started")) -> Not started | U13: =IF(D13>=1,"-",IF(C13<TEXT(TODAY(),"yyyy-mm"),"Overdue",IF(B13<=TEXT(TODAY(),"yyyy-mm"),"This month","Not yet"))) -> Not yet
A14: =Tasklist!B53 -> Trial fee or free: JD silent, meeting split (lock before start) | B14: =Tasklist!D53 -> 2027-07 | C14: =Tasklist!E53 -> 2027-07 | D14: =Tasklist!K53 -> 0 | E14: =IF(AND(E$2>=$B14,E$2<=$C14),"X","") | F14: =IF(AND(F$2>=$B14,F$2<=$C14),"X","") | G14: =IF(AND(G$2>=$B14,G$2<=$C14),"X","") | H14: =IF(AND(H$2>=$B14,H$2<=$C14),"X","") | I14: =IF(AND(I$2>=$B14,I$2<=$C14),"X","") | J14: =IF(AND(J$2>=$B14,J$2<=$C14),"X","") | K14: =IF(AND(K$2>=$B14,K$2<=$C14),"X","") | L14: =IF(AND(L$2>=$B14,L$2<=$C14),"X","") | ... S14: =IF(AND(S$2>=$B14,S$2<=$C14),"X","") | T14: =IF(D14>=1,"Done",IF(D14>0,"In progress","Not started")) -> Not started | U14: =IF(D14>=1,"-",IF(C14<TEXT(TODAY(),"yyyy-mm"),"Overdue",IF(B14<=TEXT(TODAY(),"yyyy-mm"),"This month","Not yet"))) -> Not yet
A15: =Tasklist!B55 -> Regular weeks (~18h/wk) | B15: =Tasklist!D55 -> 2026-10 | C15: =Tasklist!E55 -> 2027-08 | D15: =Tasklist!K55 -> 0 | E15: =IF(AND(E$2>=$B15,E$2<=$C15),"X","") -> X | F15: =IF(AND(F$2>=$B15,F$2<=$C15),"X","") -> X | G15: =IF(AND(G$2>=$B15,G$2<=$C15),"X","") -> X | H15: =IF(AND(H$2>=$B15,H$2<=$C15),"X","") -> X | I15: =IF(AND(I$2>=$B15,I$2<=$C15),"X","") -> X | J15: =IF(AND(J$2>=$B15,J$2<=$C15),"X","") -> X | K15: =IF(AND(K$2>=$B15,K$2<=$C15),"X","") -> X | L15: =IF(AND(L$2>=$B15,L$2<=$C15),"X","") -> X | ... S15: =IF(AND(S$2>=$B15,S$2<=$C15),"X","") | T15: =IF(D15>=1,"Done",IF(D15>0,"In progress","Not started")) -> Not started | U15: =IF(D15>=1,"-",IF(C15<TEXT(TODAY(),"yyyy-mm"),"Overdue",IF(B15<=TEXT(TODAY(),"yyyy-mm"),"This month","Not yet"))) -> This month
A16: =Tasklist!B56 -> Social/commission 10%/hospitality 3% owner + caps (TBD) | B16: =Tasklist!D56 -> 2026-10 | C16: =Tasklist!E56 -> 2027-08 | D16: =Tasklist!K56 -> 0 | E16: =IF(AND(E$2>=$B16,E$2<=$C16),"X","") -> X | F16: =IF(AND(F$2>=$B16,F$2<=$C16),"X","") -> X | G16: =IF(AND(G$2>=$B16,G$2<=$C16),"X","") -> X | H16: =IF(AND(H$2>=$B16,H$2<=$C16),"X","") -> X | I16: =IF(AND(I$2>=$B16,I$2<=$C16),"X","") -> X | J16: =IF(AND(J$2>=$B16,J$2<=$C16),"X","") -> X | K16: =IF(AND(K$2>=$B16,K$2<=$C16),"X","") -> X | L16: =IF(AND(L$2>=$B16,L$2<=$C16),"X","") -> X | ... S16: =IF(AND(S$2>=$B16,S$2<=$C16),"X","") | T16: =IF(D16>=1,"Done",IF(D16>0,"In progress","Not started")) -> Not started | U16: =IF(D16>=1,"-",IF(C16<TEXT(TODAY(),"yyyy-mm"),"Overdue",IF(B16<=TEXT(TODAY(),"yyyy-mm"),"This month","Not yet"))) -> This month
A17: 2027 Revenue Calendar — from BREAK EVEN model (¥1,056,000) | E17: =IF(AND(E$2>=$B17,E$2<=$C17),"X","") | F17: =IF(AND(F$2>=$B17,F$2<=$C17),"X","") | G17: =IF(AND(G$2>=$B17,G$2<=$C17),"X","") | H17: =IF(AND(H$2>=$B17,H$2<=$C17),"X","") | I17: =IF(AND(I$2>=$B17,I$2<=$C17),"X","") | J17: =IF(AND(J$2>=$B17,J$2<=$C17),"X","") | K17: =IF(AND(K$2>=$B17,K$2<=$C17),"X","") | L17: =IF(AND(L$2>=$B17,L$2<=$C17),"X","") | ... S17: =IF(AND(S$2>=$B17,S$2<=$C17),"X","")
A18: Winter camp — 3 weeks (Jan) | B18: 2027-01 | C18: 2027-01 | D18: 0 | E18: =IF(AND(E$2>=$B18,E$2<=$C18),"X","") | F18: =IF(AND(F$2>=$B18,F$2<=$C18),"X","") | G18: =IF(AND(G$2>=$B18,G$2<=$C18),"X","") | H18: =IF(AND(H$2>=$B18,H$2<=$C18),"X","") -> X | I18: =IF(AND(I$2>=$B18,I$2<=$C18),"X","") | J18: =IF(AND(J$2>=$B18,J$2<=$C18),"X","") | K18: =IF(AND(K$2>=$B18,K$2<=$C18),"X","") | L18: =IF(AND(L$2>=$B18,L$2<=$C18),"X","") | ... S18: =IF(AND(S$2>=$B18,S$2<=$C18),"X","") | T18: =IF(D18>=1,"Done",IF(D18>0,"In progress","Not started")) -> Not started | U18: =IF(D18>=1,"-",IF(C18<TEXT(TODAY(),"yyyy-mm"),"Overdue",IF(B18<=TEXT(TODAY(),"yyyy-mm"),"This month","Not yet"))) -> Not yet
A19: Semester intake Feb — 15 standard | B19: 2027-02 | C19: 2027-02 | D19: 0 | E19: =IF(AND(E$2>=$B19,E$2<=$C19),"X","") | F19: =IF(AND(F$2>=$B19,F$2<=$C19),"X","") | G19: =IF(AND(G$2>=$B19,G$2<=$C19),"X","") | H19: =IF(AND(H$2>=$B19,H$2<=$C19),"X","") | I19: =IF(AND(I$2>=$B19,I$2<=$C19),"X","") -> X | J19: =IF(AND(J$2>=$B19,J$2<=$C19),"X","") | K19: =IF(AND(K$2>=$B19,K$2<=$C19),"X","") | L19: =IF(AND(L$2>=$B19,L$2<=$C19),"X","") | ... S19: =IF(AND(S$2>=$B19,S$2<=$C19),"X","") | T19: =IF(D19>=1,"Done",IF(D19>0,"In progress","Not started")) -> Not started | U19: =IF(D19>=1,"-",IF(C19<TEXT(TODAY(),"yyyy-mm"),"Overdue",IF(B19<=TEXT(TODAY(),"yyyy-mm"),"This month","Not yet"))) -> Not yet
A20: May camp — 1 week | B20: 2027-05 | C20: 2027-05 | D20: 0 | E20: =IF(AND(E$2>=$B20,E$2<=$C20),"X","") | F20: =IF(AND(F$2>=$B20,F$2<=$C20),"X","") | G20: =IF(AND(G$2>=$B20,G$2<=$C20),"X","") | H20: =IF(AND(H$2>=$B20,H$2<=$C20),"X","") | I20: =IF(AND(I$2>=$B20,I$2<=$C20),"X","") | J20: =IF(AND(J$2>=$B20,J$2<=$C20),"X","") | K20: =IF(AND(K$2>=$B20,K$2<=$C20),"X","") | L20: =IF(AND(L$2>=$B20,L$2<=$C20),"X","") -> X | ... S20: =IF(AND(S$2>=$B20,S$2<=$C20),"X","") | T20: =IF(D20>=1,"Done",IF(D20>0,"In progress","Not started")) -> Not started | U20: =IF(D20>=1,"-",IF(C20<TEXT(TODAY(),"yyyy-mm"),"Overdue",IF(B20<=TEXT(TODAY(),"yyyy-mm"),"This month","Not yet"))) -> Not yet
A21: Summer camp Jul — 3 weeks | B21: 2027-07 | C21: 2027-07 | D21: 0 | E21: =IF(AND(E$2>=$B21,E$2<=$C21),"X","") | F21: =IF(AND(F$2>=$B21,F$2<=$C21),"X","") | G21: =IF(AND(G$2>=$B21,G$2<=$C21),"X","") | H21: =IF(AND(H$2>=$B21,H$2<=$C21),"X","") | I21: =IF(AND(I$2>=$B21,I$2<=$C21),"X","") | J21: =IF(AND(J$2>=$B21,J$2<=$C21),"X","") | K21: =IF(AND(K$2>=$B21,K$2<=$C21),"X","") | L21: =IF(AND(L$2>=$B21,L$2<=$C21),"X","") | ... S21: =IF(AND(S$2>=$B21,S$2<=$C21),"X","") | T21: =IF(D21>=1,"Done",IF(D21>0,"In progress","Not started")) -> Not started | U21: =IF(D21>=1,"-",IF(C21<TEXT(TODAY(),"yyyy-mm"),"Overdue",IF(B21<=TEXT(TODAY(),"yyyy-mm"),"This month","Not yet"))) -> Not yet
A22: Summer camp Aug — 3 weeks | B22: 2027-08 | C22: 2027-08 | D22: 0 | E22: =IF(AND(E$2>=$B22,E$2<=$C22),"X","") | F22: =IF(AND(F$2>=$B22,F$2<=$C22),"X","") | G22: =IF(AND(G$2>=$B22,G$2<=$C22),"X","") | H22: =IF(AND(H$2>=$B22,H$2<=$C22),"X","") | I22: =IF(AND(I$2>=$B22,I$2<=$C22),"X","") | J22: =IF(AND(J$2>=$B22,J$2<=$C22),"X","") | K22: =IF(AND(K$2>=$B22,K$2<=$C22),"X","") | L22: =IF(AND(L$2>=$B22,L$2<=$C22),"X","") | ... S22: =IF(AND(S$2>=$B22,S$2<=$C22),"X","") | T22: =IF(D22>=1,"Done",IF(D22>0,"In progress","Not started")) -> Not started | U22: =IF(D22>=1,"-",IF(C22<TEXT(TODAY(),"yyyy-mm"),"Overdue",IF(B22<=TEXT(TODAY(),"yyyy-mm"),"This month","Not yet"))) -> Not yet
A23: Semester intake Sep — 15 standard | B23: 2027-09 | C23: 2027-09 | D23: 0 | E23: =IF(AND(E$2>=$B23,E$2<=$C23),"X","") | F23: =IF(AND(F$2>=$B23,F$2<=$C23),"X","") | G23: =IF(AND(G$2>=$B23,G$2<=$C23),"X","") | H23: =IF(AND(H$2>=$B23,H$2<=$C23),"X","") | I23: =IF(AND(I$2>=$B23,I$2<=$C23),"X","") | J23: =IF(AND(J$2>=$B23,J$2<=$C23),"X","") | K23: =IF(AND(K$2>=$B23,K$2<=$C23),"X","") | L23: =IF(AND(L$2>=$B23,L$2<=$C23),"X","") | ... S23: =IF(AND(S$2>=$B23,S$2<=$C23),"X","") | T23: =IF(D23>=1,"Done",IF(D23>0,"In progress","Not started")) -> Not started | U23: =IF(D23>=1,"-",IF(C23<TEXT(TODAY(),"yyyy-mm"),"Overdue",IF(B23<=TEXT(TODAY(),"yyyy-mm"),"This month","Not yet"))) -> Not yet
A24: Oct camp — 1 week | B24: 2027-10 | C24: 2027-10 | D24: 0 | E24: =IF(AND(E$2>=$B24,E$2<=$C24),"X","") | F24: =IF(AND(F$2>=$B24,F$2<=$C24),"X","") | G24: =IF(AND(G$2>=$B24,G$2<=$C24),"X","") | H24: =IF(AND(H$2>=$B24,H$2<=$C24),"X","") | I24: =IF(AND(I$2>=$B24,I$2<=$C24),"X","") | J24: =IF(AND(J$2>=$B24,J$2<=$C24),"X","") | K24: =IF(AND(K$2>=$B24,K$2<=$C24),"X","") | L24: =IF(AND(L$2>=$B24,L$2<=$C24),"X","") | ... S24: =IF(AND(S$2>=$B24,S$2<=$C24),"X","") | T24: =IF(D24>=1,"Done",IF(D24>0,"In progress","Not started")) -> Not started | U24: =IF(D24>=1,"-",IF(C24<TEXT(TODAY(),"yyyy-mm"),"Overdue",IF(B24<=TEXT(TODAY(),"yyyy-mm"),"This month","Not yet"))) -> Not yet
A25: CCA rolling — 25 kids a month | B25: 2026-10 | C25: 2027-12 | D25: 0 | E25: =IF(AND(E$2>=$B25,E$2<=$C25),"X","") -> X | F25: =IF(AND(F$2>=$B25,F$2<=$C25),"X","") -> X | G25: =IF(AND(G$2>=$B25,G$2<=$C25),"X","") -> X | H25: =IF(AND(H$2>=$B25,H$2<=$C25),"X","") -> X | I25: =IF(AND(I$2>=$B25,I$2<=$C25),"X","") -> X | J25: =IF(AND(J$2>=$B25,J$2<=$C25),"X","") -> X | K25: =IF(AND(K$2>=$B25,K$2<=$C25),"X","") -> X | L25: =IF(AND(L$2>=$B25,L$2<=$C25),"X","") -> X | ... S25: =IF(AND(S$2>=$B25,S$2<=$C25),"X","") -> X | T25: =IF(D25>=1,"Done",IF(D25>0,"In progress","Not started")) -> Not started | U25: =IF(D25>=1,"-",IF(C25<TEXT(TODAY(),"yyyy-mm"),"Overdue",IF(B25<=TEXT(TODAY(),"yyyy-mm"),"This month","Not yet"))) -> This month
A26: Key dates — from the meeting recording | E26: =IF(AND(E$2>=$B26,E$2<=$C26),"X","") | F26: =IF(AND(F$2>=$B26,F$2<=$C26),"X","") | G26: =IF(AND(G$2>=$B26,G$2<=$C26),"X","") | H26: =IF(AND(H$2>=$B26,H$2<=$C26),"X","") | I26: =IF(AND(I$2>=$B26,I$2<=$C26),"X","") | J26: =IF(AND(J$2>=$B26,J$2<=$C26),"X","") | K26: =IF(AND(K$2>=$B26,K$2<=$C26),"X","") | L26: =IF(AND(L$2>=$B26,L$2<=$C26),"X","") | ... S26: =IF(AND(S$2>=$B26,S$2<=$C26),"X","")
A27: Halloween event (Oct 31, after 15:00) | B27: 2026-10 | C27: 2026-10 | D27: 0 | E27: =IF(AND(E$2>=$B27,E$2<=$C27),"X","") -> X | F27: =IF(AND(F$2>=$B27,F$2<=$C27),"X","") | G27: =IF(AND(G$2>=$B27,G$2<=$C27),"X","") | H27: =IF(AND(H$2>=$B27,H$2<=$C27),"X","") | I27: =IF(AND(I$2>=$B27,I$2<=$C27),"X","") | J27: =IF(AND(J$2>=$B27,J$2<=$C27),"X","") | K27: =IF(AND(K$2>=$B27,K$2<=$C27),"X","") | L27: =IF(AND(L$2>=$B27,L$2<=$C27),"X","") | ... S27: =IF(AND(S$2>=$B27,S$2<=$C27),"X","") | T27: =IF(D27>=1,"Done",IF(D27>0,"In progress","Not started")) -> Not started | U27: =IF(D27>=1,"-",IF(C27<TEXT(TODAY(),"yyyy-mm"),"Overdue",IF(B27<=TEXT(TODAY(),"yyyy-mm"),"This month","Not yet"))) -> This month
A28: CCA closing gifts (mid-Nov) | B28: 2026-11 | C28: 2026-11 | D28: 0 | E28: =IF(AND(E$2>=$B28,E$2<=$C28),"X","") | F28: =IF(AND(F$2>=$B28,F$2<=$C28),"X","") -> X | G28: =IF(AND(G$2>=$B28,G$2<=$C28),"X","") | H28: =IF(AND(H$2>=$B28,H$2<=$C28),"X","") | I28: =IF(AND(I$2>=$B28,I$2<=$C28),"X","") | J28: =IF(AND(J$2>=$B28,J$2<=$C28),"X","") | K28: =IF(AND(K$2>=$B28,K$2<=$C28),"X","") | L28: =IF(AND(L$2>=$B28,L$2<=$C28),"X","") | ... S28: =IF(AND(S$2>=$B28,S$2<=$C28),"X","") | T28: =IF(D28>=1,"Done",IF(D28>0,"In progress","Not started")) -> Not started | U28: =IF(D28>=1,"-",IF(C28<TEXT(TODAY(),"yyyy-mm"),"Overdue",IF(B28<=TEXT(TODAY(),"yyyy-mm"),"This month","Not yet"))) -> Not yet
A29: Winter camp window (Dec 24 - Jan 7) | B29: 2026-12 | C29: 2027-01 | D29: 0 | E29: =IF(AND(E$2>=$B29,E$2<=$C29),"X","") | F29: =IF(AND(F$2>=$B29,F$2<=$C29),"X","") | G29: =IF(AND(G$2>=$B29,G$2<=$C29),"X","") -> X | H29: =IF(AND(H$2>=$B29,H$2<=$C29),"X","") -> X | I29: =IF(AND(I$2>=$B29,I$2<=$C29),"X","") | J29: =IF(AND(J$2>=$B29,J$2<=$C29),"X","") | K29: =IF(AND(K$2>=$B29,K$2<=$C29),"X","") | L29: =IF(AND(L$2>=$B29,L$2<=$C29),"X","") | ... S29: =IF(AND(S$2>=$B29,S$2<=$C29),"X","") | T29: =IF(D29>=1,"Done",IF(D29>0,"In progress","Not started")) -> Not started | U29: =IF(D29>=1,"-",IF(C29<TEXT(TODAY(),"yyyy-mm"),"Overdue",IF(B29<=TEXT(TODAY(),"yyyy-mm"),"This month","Not yet"))) -> Not yet
A30: End-of-semester showcase / art party | B30: 2026-12 | C30: 2026-12 | D30: 0 | E30: =IF(AND(E$2>=$B30,E$2<=$C30),"X","") | F30: =IF(AND(F$2>=$B30,F$2<=$C30),"X","") | G30: =IF(AND(G$2>=$B30,G$2<=$C30),"X","") -> X | H30: =IF(AND(H$2>=$B30,H$2<=$C30),"X","") | I30: =IF(AND(I$2>=$B30,I$2<=$C30),"X","") | J30: =IF(AND(J$2>=$B30,J$2<=$C30),"X","") | K30: =IF(AND(K$2>=$B30,K$2<=$C30),"X","") | L30: =IF(AND(L$2>=$B30,L$2<=$C30),"X","") | ... S30: =IF(AND(S$2>=$B30,S$2<=$C30),"X","") | T30: =IF(D30>=1,"Done",IF(D30>0,"In progress","Not started")) -> Not started | U30: =IF(D30>=1,"-",IF(C30<TEXT(TODAY(),"yyyy-mm"),"Overdue",IF(B30<=TEXT(TODAY(),"yyyy-mm"),"This month","Not yet"))) -> Not yet

Sheet Compliance
A1: Compliance | F1: =HYPERLINK("#'Cover'!A1","←") -> ←
A2: Area | B2: Rule / Topic | C2: What to do | D2: Official link | E2: Review
A3: Training | B3: 民办教育/工作室 vs 培训机构边界 (Private education vs studio boundary) | C3: studio口径：assistance/consulting，不宣称学历教育 (Studio line: assistance/consulting, no schooling claims) | D3: gov.cn 搜索 民办教育促进法 (gov.cn: Private Education Promotion Law) | E3: Quarterly
A4: Children | B4: 未成年人保护：8岁以上本人+监护人双签 (Minors: dual sign (child 8+ + guardian)) | C4: 同意书双签 (Dual-signature consent) | D4: npc.gov.cn 未成年人保护法 (npc.gov.cn: Minors Protection Law) | E4: Per signing
A5: Portrait | B5: 肖像权：签了才能拍，撤回15日删 (Portrait rights: sign first, delete in 15 days on withdrawal) | C5: Consents表+V1话术 (Consents sheet + V1 script) | D5: 民法典第1018-1022条 (Civil Code Art. 1018-1022) | E5: Per shoot
A6: Data | B6: 儿童个人信息最小必要、不外传 (Children data: minimum necessary, never shared) | C6: 共享文档最小权限 (Least-privilege sharing) | D6: CAC 儿童个人信息保护 (CAC: child data rules) | E6: Monthly
A7: Food | B7: 冬令营午餐： 留样 (Camp lunch: licensed venue + samples kept) | C7: WinterCamp备注列 (WinterCamp notes col) | D7: 市场监管总局 校园餐 (SAMR: school meals) | E7: Per camp
A8: Safety | B8: 大型装置防风防雨+保险 (Big installs: wind/rain plan + insurance) | C8: Events报备单 (Events permit sheet) | D8: EKA物业 + 保险经纪 (EKA mgmt + broker) | E8: Per event
A9: Tax | B9: Service invoices + IIT handling (office admin) | C9: Approvals+Expenses留凭 (Keep vouchers in Approvals+Expenses) | D9: 12366 纳税服务 (12366 tax service) | E9: Monthly
A10: Ads | B10: 广告法：不承诺升学/获奖 (Ads: never promise admissions/awards) | C10: 海报话术过审 (Scripts cleared for posters) | D10: 广告法第9/24条 (Advertising Law Art. 9/24) | E10: Per poster
A11: IP | B11: 课程被抄：时间戳+存档 (Anti-copy: timestamp + archive) | C11: Programs版本日期 (Programs version dates) | D11: 版权局登记指南 (Copyright Office guide) | E11: Per term

Sheet AntiFraud
A1: Anti-Fraud | J1: =HYPERLINK("#'Cover'!A1","←") -> ←
A2: # | B2: Risk | C2: What happened (meeting) | D2: Early signal | E2: Rule now | F2: Next action (this week) | G2: Due | H2: Owner | I2: Status
A3: F-01 | B3: Curriculum theft | C3: UN-era partner (CN lady, no EN): learned full system, fired, took students cut-price, opened Shun Space copying programs monthly incl obscure artists | D3: Same program next month on her channel | E3: Full methods never leave studio. Showcases show works not methods. Timestamp Programs. NDA for partners. | F3: Archive Shun Space screenshots with dates (defense file) | G3: This week | H3: TBD | I3: Open
A4: F-02 | B4: Contact theft | C4: Ex-colleague took all parent contacts; Danny lost students he can't name | D4: Side-channel adds | E4: One official channel only. Leads Owner = Studio official. No private adds. Offboarding revokes day one. | F4: Audit all parent contacts: Owner=official, delete side channels | G4: This week | H4: TBD | I4: Open
A5: F-03 | B5: Exhibition cut unknown | C5: Beijing lady runs intl shows (JP/IT/BJ/HK), cut % never discussed; also signed Shun Space | D5: Invoice without agreed split | E5: No show without Agreed cut % + signed confirmation (Exhibitions I/J). Amber bridge terms in writing. | F5: Email Beijing lady: ask cut % + written terms before Jan show | G5: This week | H5: TBD | I5: Open
A6: F-04 | B6: Price undercut | C6: Copycat lower price with stolen program | D6: Parent mentions cheaper same program | E6: 400 list price defended by tailor-made story. Discounts enclosed + signed, never public. | F6: Lock 400 price story in Scripts T1; enclosed-discount rule live | G6: This week | H6: TBD | I6: Open
A7: F-05 | B7: Photo/video misuse | C7: Past photos/videos reused to build copycat program | D7: Our process videos appear elsewhere | E7: Consents signed first. Watermark process videos. No raw footage out. | F7: Watermark all process videos; raw footage stays inside | G7: Ongoing | H7: TBD | I7: Open

Sheet SOP
A1: Daily SOP | F1: =HYPERLINK("#'Cover'!A1","←") -> ←
A2: Step | B2: Do this now | C2: Go to | D2: Done? | E2: Result
A3: 1 | B3: Review Dashboard — note renewals, at-risk families, outstanding bills | C3: =HYPERLINK("#'Dashboard'!A1","Dashboard") -> Dashboard | E3: Jot the 3 numbers here
A4: 2 | B4: Telephone families due to renew (Script R1) | C4: =HYPERLINK("#'Students'!A1","Students") -> Students | E4: renewals in
A5: 3 | B5: Visit with unsettled families (Script M2) | C5: =HYPERLINK("#'Makeup_Churn'!A1","Makeup_Churn") -> Makeup_Churn | E5: families kept
A6: 4 | B6: Remind outstanding bills with courtesy (Script P1) | C6: =HYPERLINK("#'Invoices'!A1","Invoices") -> Invoices | E6: ¥ collected
A7: 5 | B7: Register two new enquiries with source | C7: =HYPERLINK("#'Leads'!A1","Leads") -> Leads | E7: 2 new leads
A8: 6 | B8: Invite one family to trial (Script T1) | C8: =HYPERLINK("#'Trials'!A1","Trials") -> Trials | E8: 1 trial set
A9: 7 | B9: Publish one film (consent confirmed first) | C9: =HYPERLINK("#'Consents'!A1","Consents") -> Consents | E9: 1 video posted
A10: 8 | B10: Mark Done% so the Gantt follows | C10: =HYPERLINK("#'Tasklist'!A1","Tasklist") -> Tasklist | E10: Gantt updated

Sheet Showcase
A1: Showcase Plan | G1: =HYPERLINK("#'Cover'!A1","←") -> ←
A2: Phase | B2: Task | C2: Owner | D2: Done? | E2: Materials / People | F2: Deadline
A3: T-14 days | B3: Fix date: Saturday after 15:00 (classes run till 15:00). Book the studio half, keep one corner for works display. | C3: TBD | E3: Studio floor plan; nothing else that afternoon
A4: T-14 days | B4: Send S1 invite on the official account to every family. Ask: headcount incl. grandparents. | C4: TBD | E4: Scripts S1; reply-with-headcount
A5: T-10 days | B5: Each child picks ONE finished work + writes a 3-line card: what / how / what I learned. | C5: TBD | E5: Intro cards, wall labels
A6: T-7 days | B6: Collect signed consents: photo yes/no, video yes/no, close-up needs a separate tick, school-channel publish separate tick. No signed row = no camera, no exceptions. | C6: TBD | E6: Consents sheet + V1 script; tablet sign-off
A7: T-7 days | B7: Print certificates: child name + program/artist + hours + technique + one-line concept + teacher signature. Wording is a record of study, not a licensed diploma. | C7: TBD | E7: Certificates sheet; check hours against Students
A8: T-7 days | B8: Print the run-of-show and assign 3 roles: Host (welcomes, keeps time), Teacher (introduces each child), Helper (music, snacks, photos of consented kids only). | C8: TBD | E8: One-page run sheet
A9: T-3 days | B9: Rehearse: each child 5 minutes with a timer. Teacher listens once, fixes one thing only. | C9: TBD | E9: Timer, floor marks
A10: T-3 days | B10: Buy: juice + biscuits + stickers + printed QR codes (official account + referral card). | C10: TBD | E10: Events sheet
A11: T-1 day | B11: Charge phones + tripod. Test one 10-second clip: check light, sound, faces of consented kids. | C11: TBD | E11: Phones, tripod, charger
A12: Show day 15:00 | B12: Doors + sign-in desk FIRST: every family leaves child name + parent phone + WeChat. (Past lesson: visitors came, no contacts stayed.) | C12: TBD | E12: Sign-in sheet — never skip
A13: Show day 15:15 | B13: Host opens (3 min max): what the kids made this term, one sentence on the studio's way of teaching. | C13: TBD | E13: Host lines on run sheet
A14: Show day 15:20 | B14: Kids present ~5 min each. Helper films ONLY consented kids, white-canvas-to-finish clips where available. | C14: TBD | E14: Timer visible to kids
A15: Show day 16:00 | B15: Certificates + family photos + mingle. Helper hands referral cards (G1, no public discount talk). | C15: TBD | E15: Certificates, G1 cards
A16: Show day 16:30 | B16: Close on time. Thank each family by name at the door. | C16: TBD
A17: T+1 day | B17: Send T1 to every visiting non-client family + enrolment pack. Log all in Trials/Leads within 24h. | C17: TBD | E17: Trials sheet, Send_Kit
A18: T+3 days | B18: Post the short film (consented kids only) + ask 3 happy parents for a one-line review. | C18: TBD | E18: G1 script, social accounts
A19: T+7 days | B19: Count: visitors / trials booked / enrolled. Write the number in Channel_Pivot notes. | C19: TBD | E19: Channel_Pivot

Sheet BirthdayWS
A1: Birthday Plan | G1: =HYPERLINK("#'Cover'!A1","←") -> ←
A2: Phase | B2: Task | C2: Owner | D2: Done? | E2: Materials / People | F2: Fee
A3: T-14 days | B3: Confirm with the birthday family: theme + 2-hour slot + headcount (default 6-8 kids; 20-kid scale only if the family asks). Rule: the birthday family pays for all guests. | C3: TBD | E3: Theme list (animals/flowers/season); fee TBD openly
A4: T-10 days | B4: Guest list with phones: collect every guest parent's phone + WeChat at invite time. (Past lesson: 20 kids came once, zero contacts stayed.) | C4: TBD | E4: Invite cards via official account
A5: T-7 days | B5: Prep one kit per kid: canvas/paper + paints + apron + name sticker. Count twice. | C5: TBD | E5: Events sheet
A6: T-7 days | B6: Ask: food allergies + photo consent per guest child. Cake note: candles, no nuts unless confirmed. | C6: TBD | E6: Consents sheet
A7: T-3 days | B7: Order cake + juice + biscuits. Playlist + 2 simple games ready (backup if paint dries slow). | C7: TBD | E7: Cake order; fee: birthday family
A8: Party 0:00 | B8: Welcome + name stickers + hand wash. Helper photographs consented kids only. | C8: TBD | E8: Stickers, camera
A9: Party 0:15 | B9: Game 1 (10 min) to settle the group, then sit down to make. | C9: TBD | E9: Game props
A10: Party 0:30 | B10: Make: every child finishes ONE artwork to take home. Teacher rescues, never remakes. | C10: TBD | E10: Kits; frames optional, extra charge stated upfront
A11: Party 1:30 | B11: Cake + song + group photo (consented kids). Hand each guest: QR card + referral card. | C11: TBD | E11: G1 cards
A12: Party 1:50 | B12: Show & tell: each child holds up their work, one sentence. Clap for everyone. | C12: TBD
A13: T+1 day | B13: Thank-you message to every guest family + trial invite (T1). Log all in Trials/Leads. | C13: TBD | E13: Trials sheet
A14: T+3 days | B14: Book trials into this week's slots. Track guest-to-trial in Channel_Pivot. | C14: TBD | E14: Leads, Channel_Pivot

Sheet HalloweenPlan
A1: Halloween Plan | G1: =HYPERLINK("#'Cover'!A1","←") -> ←
A2: Phase | B2: Task | C2: Owner | D2: Done? | E2: Materials / People | F2: Cost
A3: Now | B3: Ask EKA: outdoor spot + free/paid + can we charge + fair booth dates | C3: TBD | E3: EKA contract, permits
A4: Now | B4: Buy real pumpkins early + count tables | C4: TBD | E4: M-15, tables in studio
A5: T-7 days | B5: Build 2 pumpkins (1 big 1 small): noodles + fabric + iron core | C5: TBD | E5: Noodles, gold fabric, iron core, 1 afternoon | F5: Low
A6: T-7 days | B6: Window + lift ads live | C6: TBD | E6: Signage guy, 3 days
A7: T-3 days | B7: Posters 100 + QR + stickers pack | C7: TBD | E7: Halloween flyer EN HD
A8: Oct 31 15:00+ | B8: Carve or paint pumpkins, 10 kids/batch | C8: TBD | E8: Real pumpkins, tools, aprons | F8: Small fee
A9: Oct 31 night | B9: Party option Fri night (Halloween always night) | C9: TBD | E9: Music, lights, rain plan
A10: Oct 31 | B10: Giant pumpkin stays outdoor, photos + leads | C10: TBD | E10: QR everywhere, referral cards | F10: Free
A11: T+1 day | B11: Thank-you + trial invites to all families | C11: TBD | E11: Trials T1
A12: T+3 days | B12: Convert → trials → enrolments | C12: TBD | E12: Leads, Channel_Pivot

Sheet Certificate
A1: Completion Certificate | B1: =HYPERLINK("#'Cover'!A1","←") -> ←

Sheet Sales2027
A1: 2027 Sales Plan vs Actual — 1,056,000 CNY (BREAK EVEN model 2026-10-09) | G1: =HYPERLINK("#'Cover'!A1","<-") -> <-
A2: Channel | B2: 2027 target CNY | C2: Actual CNY | D2: Gap | E2: Students target | F2: Students now
A3: Standard classes | B3: 420000 | C3: =SUMIF(Invoices!P3:P34,"Course",Invoices!H3:H34) -> 0 | D3: =C3-B3 -> -420000 | E3: 15 | F3: =COUNTA(Students!A3:A100) -> 5
A4: CCA programmes | B4: 240000 | C4: =SUMIFS(Invoices!H3:H34,Invoices!M3:M34,"CCA showcase",Invoices!I3:I34,"Paid") -> 0 | D4: =C4-B4 -> -240000 | E4: 25 | F4: =COUNTIF(Leads!E3:E100,"CCA showcase") -> 1
A5: Holiday camps | B5: 396000 | C5: =SUMIFS(Invoices!H3:H34,Invoices!P3:P34,"Winter camp",Invoices!I3:I34,"Paid") -> 0 | D5: =C5-B5 -> -396000 | E5: 44 | F5: =COUNTA(WinterCamp!A3:A100) -> 0
A6: TOTAL | B6: 1056000 | C6: =SUM(C3:C5) -> 0 | D6: =C6-B6 -> -1056000

Sheet PnL2027
A1: 2027 P&L vs Plan — revenue from the model, costs from the recording (fill the blue cells) | O1: =HYPERLINK("#'Cover'!A1","<-") -> <-
A2: Item | B2: Jan | C2: Feb | D2: Mar | E2: Apr | F2: May | G2: Jun | H2: Jul | I2: Aug | J2: Sep | K2: Oct | L2: Nov | M2: Dec | N2: FY 2027
A3: REVENUE TARGET (model) | N3: =SUM(B3:M3) -> 0
A4: Standard classes | B4: 42000 | C4: 42000 | D4: 42000 | E4: 42000 | F4: 42000 | G4: 42000 | H4: 0 | I4: 0 | J4: 42000 | K4: 42000 | L4: 42000 | M4: 42000 | N4: =SUM(B4:M4) -> 420000
A5: CCA programmes | B5: 20000 | C5: 20000 | D5: 20000 | E5: 20000 | F5: 20000 | G5: 20000 | H5: 20000 | I5: 20000 | J5: 20000 | K5: 20000 | L5: 20000 | M5: 20000 | N5: =SUM(B5:M5) -> 240000
A6: Holiday camps | B6: 108000 | C6: 0 | D6: 0 | E6: 0 | F6: 36000 | G6: 0 | H6: 108000 | I6: 108000 | J6: 0 | K6: 36000 | L6: 0 | M6: 0 | N6: =SUM(B6:M6) -> 396000
A7: Target total | B7: =B4+B5+B6 -> 170000 | C7: =C4+C5+C6 -> 62000 | D7: =D4+D5+D6 -> 62000 | E7: =E4+E5+E6 -> 62000 | F7: =F4+F5+F6 -> 98000 | G7: =G4+G5+G6 -> 62000 | H7: =H4+H5+H6 -> 128000 | I7: =I4+I5+I6 -> 128000 | ... M7: =M4+M5+M6 -> 62000 | N7: =SUM(B7:M7) -> 1056000
A8: REVENUE ACTUAL (paid invoices, by date) | N8: =SUM(B8:M8) -> 0
A9: Standard actual | B9: =SUMIFS(Invoices!$H$3:$H$34,Invoices!$P$3:$P$34,"Course",Invoices!$I$3:$I$34,"Paid",Invoices!$B$3:$B$34,">="&DATE(2027,1,1),Invoices!$B$3:$B$34,"<"&DATE(2027,2,1)) -> 0 | C9: =SUMIFS(Invoices!$H$3:$H$34,Invoices!$P$3:$P$34,"Course",Invoices!$I$3:$I$34,"Paid",Invoices!$B$3:$B$34,">="&DATE(2027,2,1),Invoices!$B$3:$B$34,"<"&DATE(2027,3,1)) -> 0 | D9: =SUMIFS(Invoices!$H$3:$H$34,Invoices!$P$3:$P$34,"Course",Invoices!$I$3:$I$34,"Paid",Invoices!$B$3:$B$34,">="&DATE(2027,3,1),Invoices!$B$3:$B$34,"<"&DATE(2027,4,1)) -> 0 | E9: =SUMIFS(Invoices!$H$3:$H$34,Invoices!$P$3:$P$34,"Course",Invoices!$I$3:$I$34,"Paid",Invoices!$B$3:$B$34,">="&DATE(2027,4,1),Invoices!$B$3:$B$34,"<"&DATE(2027,5,1)) -> 0 | F9: =SUMIFS(Invoices!$H$3:$H$34,Invoices!$P$3:$P$34,"Course",Invoices!$I$3:$I$34,"Paid",Invoices!$B$3:$B$34,">="&DATE(2027,5,1),Invoices!$B$3:$B$34,"<"&DATE(2027,6,1)) -> 0 | G9: =SUMIFS(Invoices!$H$3:$H$34,Invoices!$P$3:$P$34,"Course",Invoices!$I$3:$I$34,"Paid",Invoices!$B$3:$B$34,">="&DATE(2027,6,1),Invoices!$B$3:$B$34,"<"&DATE(2027,7,1)) -> 0 | H9: =SUMIFS(Invoices!$H$3:$H$34,Invoices!$P$3:$P$34,"Course",Invoices!$I$3:$I$34,"Paid",Invoices!$B$3:$B$34,">="&DATE(2027,7,1),Invoices!$B$3:$B$34,"<"&DATE(2027,8,1)) -> 0 | I9: =SUMIFS(Invoices!$H$3:$H$34,Invoices!$P$3:$P$34,"Course",Invoices!$I$3:$I$34,"Paid",Invoices!$B$3:$B$34,">="&DATE(2027,8,1),Invoices!$B$3:$B$34,"<"&DATE(2027,9,1)) -> 0 | J9: =SUMIFS(Invoices!$H$3:$H$34,Invoices!$P$3:$P$34,"Course",Invoices!$I$3:$I$34,"Paid",Invoices!$B$3:$B$34,">="&DATE(2027,9,1),Invoices!$B$3:$B$34,"<"&DATE(2027,10,1)) -> 0 | K9: =SUMIFS(Invoices!$H$3:$H$34,Invoices!$P$3:$P$34,"Course",Invoices!$I$3:$I$34,"Paid",Invoices!$B$3:$B$34,">="&DATE(2027,10,1),Invoices!$B$3:$B$34,"<"&DATE(2027,11,1)) -> 0 | L9: =SUMIFS(Invoices!$H$3:$H$34,Invoices!$P$3:$P$34,"Course",Invoices!$I$3:$I$34,"Paid",Invoices!$B$3:$B$34,">="&DATE(2027,11,1),Invoices!$B$3:$B$34,"<"&DATE(2027,12,1)) -> 0 | M9: =SUMIFS(Invoices!$H$3:$H$34,Invoices!$P$3:$P$34,"Course",Invoices!$I$3:$I$34,"Paid",Invoices!$B$3:$B$34,">="&DATE(2027,12,1),Invoices!$B$3:$B$34,"<"&DATE(2028,1,1)) -> 0 | N9: =SUM(B9:M9) -> 0
A10: CCA actual | B10: =SUMIFS(Invoices!$H$3:$H$34,Invoices!$M$3:$M$34,"CCA showcase",Invoices!$I$3:$I$34,"Paid",Invoices!$B$3:$B$34,">="&DATE(2027,1,1),Invoices!$B$3:$B$34,"<"&DATE(2027,2,1)) -> 0 | C10: =SUMIFS(Invoices!$H$3:$H$34,Invoices!$M$3:$M$34,"CCA showcase",Invoices!$I$3:$I$34,"Paid",Invoices!$B$3:$B$34,">="&DATE(2027,2,1),Invoices!$B$3:$B$34,"<"&DATE(2027,3,1)) -> 0 | D10: =SUMIFS(Invoices!$H$3:$H$34,Invoices!$M$3:$M$34,"CCA showcase",Invoices!$I$3:$I$34,"Paid",Invoices!$B$3:$B$34,">="&DATE(2027,3,1),Invoices!$B$3:$B$34,"<"&DATE(2027,4,1)) -> 0 | E10: =SUMIFS(Invoices!$H$3:$H$34,Invoices!$M$3:$M$34,"CCA showcase",Invoices!$I$3:$I$34,"Paid",Invoices!$B$3:$B$34,">="&DATE(2027,4,1),Invoices!$B$3:$B$34,"<"&DATE(2027,5,1)) -> 0 | F10: =SUMIFS(Invoices!$H$3:$H$34,Invoices!$M$3:$M$34,"CCA showcase",Invoices!$I$3:$I$34,"Paid",Invoices!$B$3:$B$34,">="&DATE(2027,5,1),Invoices!$B$3:$B$34,"<"&DATE(2027,6,1)) -> 0 | G10: =SUMIFS(Invoices!$H$3:$H$34,Invoices!$M$3:$M$34,"CCA showcase",Invoices!$I$3:$I$34,"Paid",Invoices!$B$3:$B$34,">="&DATE(2027,6,1),Invoices!$B$3:$B$34,"<"&DATE(2027,7,1)) -> 0 | H10: =SUMIFS(Invoices!$H$3:$H$34,Invoices!$M$3:$M$34,"CCA showcase",Invoices!$I$3:$I$34,"Paid",Invoices!$B$3:$B$34,">="&DATE(2027,7,1),Invoices!$B$3:$B$34,"<"&DATE(2027,8,1)) -> 0 | I10: =SUMIFS(Invoices!$H$3:$H$34,Invoices!$M$3:$M$34,"CCA showcase",Invoices!$I$3:$I$34,"Paid",Invoices!$B$3:$B$34,">="&DATE(2027,8,1),Invoices!$B$3:$B$34,"<"&DATE(2027,9,1)) -> 0 | J10: =SUMIFS(Invoices!$H$3:$H$34,Invoices!$M$3:$M$34,"CCA showcase",Invoices!$I$3:$I$34,"Paid",Invoices!$B$3:$B$34,">="&DATE(2027,9,1),Invoices!$B$3:$B$34,"<"&DATE(2027,10,1)) -> 0 | K10: =SUMIFS(Invoices!$H$3:$H$34,Invoices!$M$3:$M$34,"CCA showcase",Invoices!$I$3:$I$34,"Paid",Invoices!$B$3:$B$34,">="&DATE(2027,10,1),Invoices!$B$3:$B$34,"<"&DATE(2027,11,1)) -> 0 | L10: =SUMIFS(Invoices!$H$3:$H$34,Invoices!$M$3:$M$34,"CCA showcase",Invoices!$I$3:$I$34,"Paid",Invoices!$B$3:$B$34,">="&DATE(2027,11,1),Invoices!$B$3:$B$34,"<"&DATE(2027,12,1)) -> 0 | M10: =SUMIFS(Invoices!$H$3:$H$34,Invoices!$M$3:$M$34,"CCA showcase",Invoices!$I$3:$I$34,"Paid",Invoices!$B$3:$B$34,">="&DATE(2027,12,1),Invoices!$B$3:$B$34,"<"&DATE(2028,1,1)) -> 0 | N10: =SUM(B10:M10) -> 0
A11: Camps actual | B11: =SUMIFS(Invoices!$H$3:$H$34,Invoices!$P$3:$P$34,"*camp*",Invoices!$I$3:$I$34,"Paid",Invoices!$B$3:$B$34,">="&DATE(2027,1,1),Invoices!$B$3:$B$34,"<"&DATE(2027,2,1)) -> 0 | C11: =SUMIFS(Invoices!$H$3:$H$34,Invoices!$P$3:$P$34,"*camp*",Invoices!$I$3:$I$34,"Paid",Invoices!$B$3:$B$34,">="&DATE(2027,2,1),Invoices!$B$3:$B$34,"<"&DATE(2027,3,1)) -> 0 | D11: =SUMIFS(Invoices!$H$3:$H$34,Invoices!$P$3:$P$34,"*camp*",Invoices!$I$3:$I$34,"Paid",Invoices!$B$3:$B$34,">="&DATE(2027,3,1),Invoices!$B$3:$B$34,"<"&DATE(2027,4,1)) -> 0 | E11: =SUMIFS(Invoices!$H$3:$H$34,Invoices!$P$3:$P$34,"*camp*",Invoices!$I$3:$I$34,"Paid",Invoices!$B$3:$B$34,">="&DATE(2027,4,1),Invoices!$B$3:$B$34,"<"&DATE(2027,5,1)) -> 0 | F11: =SUMIFS(Invoices!$H$3:$H$34,Invoices!$P$3:$P$34,"*camp*",Invoices!$I$3:$I$34,"Paid",Invoices!$B$3:$B$34,">="&DATE(2027,5,1),Invoices!$B$3:$B$34,"<"&DATE(2027,6,1)) -> 0 | G11: =SUMIFS(Invoices!$H$3:$H$34,Invoices!$P$3:$P$34,"*camp*",Invoices!$I$3:$I$34,"Paid",Invoices!$B$3:$B$34,">="&DATE(2027,6,1),Invoices!$B$3:$B$34,"<"&DATE(2027,7,1)) -> 0 | H11: =SUMIFS(Invoices!$H$3:$H$34,Invoices!$P$3:$P$34,"*camp*",Invoices!$I$3:$I$34,"Paid",Invoices!$B$3:$B$34,">="&DATE(2027,7,1),Invoices!$B$3:$B$34,"<"&DATE(2027,8,1)) -> 0 | I11: =SUMIFS(Invoices!$H$3:$H$34,Invoices!$P$3:$P$34,"*camp*",Invoices!$I$3:$I$34,"Paid",Invoices!$B$3:$B$34,">="&DATE(2027,8,1),Invoices!$B$3:$B$34,"<"&DATE(2027,9,1)) -> 0 | J11: =SUMIFS(Invoices!$H$3:$H$34,Invoices!$P$3:$P$34,"*camp*",Invoices!$I$3:$I$34,"Paid",Invoices!$B$3:$B$34,">="&DATE(2027,9,1),Invoices!$B$3:$B$34,"<"&DATE(2027,10,1)) -> 0 | K11: =SUMIFS(Invoices!$H$3:$H$34,Invoices!$P$3:$P$34,"*camp*",Invoices!$I$3:$I$34,"Paid",Invoices!$B$3:$B$34,">="&DATE(2027,10,1),Invoices!$B$3:$B$34,"<"&DATE(2027,11,1)) -> 0 | L11: =SUMIFS(Invoices!$H$3:$H$34,Invoices!$P$3:$P$34,"*camp*",Invoices!$I$3:$I$34,"Paid",Invoices!$B$3:$B$34,">="&DATE(2027,11,1),Invoices!$B$3:$B$34,"<"&DATE(2027,12,1)) -> 0 | M11: =SUMIFS(Invoices!$H$3:$H$34,Invoices!$P$3:$P$34,"*camp*",Invoices!$I$3:$I$34,"Paid",Invoices!$B$3:$B$34,">="&DATE(2027,12,1),Invoices!$B$3:$B$34,"<"&DATE(2028,1,1)) -> 0 | N11: =SUM(B11:M11) -> 0
A12: Actual total | B12: =B9+B10+B11 -> 0 | C12: =C9+C10+C11 -> 0 | D12: =D9+D10+D11 -> 0 | E12: =E9+E10+E11 -> 0 | F12: =F9+F10+F11 -> 0 | G12: =G9+G10+G11 -> 0 | H12: =H9+H10+H11 -> 0 | I12: =I9+I10+I11 -> 0 | ... M12: =M9+M10+M11 -> 0 | N12: =SUM(B12:M12) -> 0
A13: Gap (actual-target) | B13: =B12-B7 -> -170000 | C13: =C12-C7 -> -62000 | D13: =D12-D7 -> -62000 | E13: =E12-E7 -> -62000 | F13: =F12-F7 -> -98000 | G13: =G12-G7 -> -62000 | H13: =H12-H7 -> -128000 | I13: =I12-I7 -> -128000 | ... M13: =M12-M7 -> -62000 | N13: =SUM(B13:M13) -> -1056000
A14: COST BUDGET (blue = fill from bills; auto lines follow actual revenue) | N14: =SUM(B14:M14) -> 0
A15: Rent + property + management (fill) | N15: =SUM(B15:M15) -> 0
A16: Utilities + electricity (fill) | N16: =SUM(B16:M16) -> 0
A17: Materials + supplies (fill) | N17: =SUM(B17:M17) -> 0
A18: Employer contributions (TBD, owners agree) | N18: =SUM(B18:M18) -> 0
A19: Staffing (TBD, owners agree) | N19: =SUM(B19:M19) -> 0
A20: Entertainment 3% (auto) | B20: =ROUND(B12*0.03,0) -> 0 | C20: =ROUND(C12*0.03,0) -> 0 | D20: =ROUND(D12*0.03,0) -> 0 | E20: =ROUND(E12*0.03,0) -> 0 | F20: =ROUND(F12*0.03,0) -> 0 | G20: =ROUND(G12*0.03,0) -> 0 | H20: =ROUND(H12*0.03,0) -> 0 | I20: =ROUND(I12*0.03,0) -> 0 | ... M20: =ROUND(M12*0.03,0) -> 0 | N20: =SUM(B20:M20) -> 0
A21: Sales commission 10% (auto) | B21: =ROUND(B12*0.1,0) -> 0 | C21: =ROUND(C12*0.1,0) -> 0 | D21: =ROUND(D12*0.1,0) -> 0 | E21: =ROUND(E12*0.1,0) -> 0 | F21: =ROUND(F12*0.1,0) -> 0 | G21: =ROUND(G12*0.1,0) -> 0 | H21: =ROUND(H12*0.1,0) -> 0 | I21: =ROUND(I12*0.1,0) -> 0 | ... M21: =ROUND(M12*0.1,0) -> 0 | N21: =SUM(B21:M21) -> 0
A22: Tax + other (fill) | N22: =SUM(B22:M22) -> 0
A23: Budget total | B23: =SUM(B15,B16,B17,B18,B19,B20,B21,B22) -> 0 | C23: =SUM(C15,C16,C17,C18,C19,C20,C21,C22) -> 0 | D23: =SUM(D15,D16,D17,D18,D19,D20,D21,D22) -> 0 | E23: =SUM(E15,E16,E17,E18,E19,E20,E21,E22) -> 0 | F23: =SUM(F15,F16,F17,F18,F19,F20,F21,F22) -> 0 | G23: =SUM(G15,G16,G17,G18,G19,G20,G21,G22) -> 0 | H23: =SUM(H15,H16,H17,H18,H19,H20,H21,H22) -> 0 | I23: =SUM(I15,I16,I17,I18,I19,I20,I21,I22) -> 0 | ... M23: =SUM(M15,M16,M17,M18,M19,M20,M21,M22) -> 0 | N23: =SUM(B23:M23) -> 0
A24: RECORDED + NET | N24: =SUM(B24:M24) -> 0
A25: Recorded spend (from Expenses, by date) | B25: =SUMIFS(Expenses!$D$3:$D$100,Expenses!$A$3:$A$100,">="&DATE(2027,1,1),Expenses!$A$3:$A$100,"<"&DATE(2027,2,1)) -> 0 | C25: =SUMIFS(Expenses!$D$3:$D$100,Expenses!$A$3:$A$100,">="&DATE(2027,2,1),Expenses!$A$3:$A$100,"<"&DATE(2027,3,1)) -> 0 | D25: =SUMIFS(Expenses!$D$3:$D$100,Expenses!$A$3:$A$100,">="&DATE(2027,3,1),Expenses!$A$3:$A$100,"<"&DATE(2027,4,1)) -> 0 | E25: =SUMIFS(Expenses!$D$3:$D$100,Expenses!$A$3:$A$100,">="&DATE(2027,4,1),Expenses!$A$3:$A$100,"<"&DATE(2027,5,1)) -> 0 | F25: =SUMIFS(Expenses!$D$3:$D$100,Expenses!$A$3:$A$100,">="&DATE(2027,5,1),Expenses!$A$3:$A$100,"<"&DATE(2027,6,1)) -> 0 | G25: =SUMIFS(Expenses!$D$3:$D$100,Expenses!$A$3:$A$100,">="&DATE(2027,6,1),Expenses!$A$3:$A$100,"<"&DATE(2027,7,1)) -> 0 | H25: =SUMIFS(Expenses!$D$3:$D$100,Expenses!$A$3:$A$100,">="&DATE(2027,7,1),Expenses!$A$3:$A$100,"<"&DATE(2027,8,1)) -> 0 | I25: =SUMIFS(Expenses!$D$3:$D$100,Expenses!$A$3:$A$100,">="&DATE(2027,8,1),Expenses!$A$3:$A$100,"<"&DATE(2027,9,1)) -> 0 | J25: =SUMIFS(Expenses!$D$3:$D$100,Expenses!$A$3:$A$100,">="&DATE(2027,9,1),Expenses!$A$3:$A$100,"<"&DATE(2027,10,1)) -> 0 | K25: =SUMIFS(Expenses!$D$3:$D$100,Expenses!$A$3:$A$100,">="&DATE(2027,10,1),Expenses!$A$3:$A$100,"<"&DATE(2027,11,1)) -> 0 | L25: =SUMIFS(Expenses!$D$3:$D$100,Expenses!$A$3:$A$100,">="&DATE(2027,11,1),Expenses!$A$3:$A$100,"<"&DATE(2027,12,1)) -> 0 | M25: =SUMIFS(Expenses!$D$3:$D$100,Expenses!$A$3:$A$100,">="&DATE(2027,12,1),Expenses!$A$3:$A$100,"<"&DATE(2028,1,1)) -> 0 | N25: =SUM(B25:M25) -> 0
A26: Net cash (actual-recorded) | B26: =B12-B25 -> 0 | C26: =C12-C25 -> 0 | D26: =D12-D25 -> 0 | E26: =E12-E25 -> 0 | F26: =F12-F25 -> 0 | G26: =G12-G25 -> 0 | H26: =H12-H25 -> 0 | I26: =I12-I25 -> 0 | ... M26: =M12-M25 -> 0 | N26: =SUM(B26:M26) -> 0

Sheet First30
A1: First 30 Days — Oct 14 to Nov 13 (do in order, tick Done) | F1: =HYPERLINK("#'Cover'!A1","<-") -> <-
A2: By | B2: Action | C2: Where | D2: Done | E2: Note
A3: Oct 17 | B3: Window + lift ads live (promised in 3 days) | C3: Tasklist / EKA
A4: Oct 17 | B4: Collect Josh 4-kid fees, discount in writing (F1) | C4: Invoices + Scripts F1 | E4: Private rate, not public
A5: Oct 18 | B5: Revive dormant credits: message Daphne-type sleepers | C5: Students + M2 | E5: 18-class sleepers first
A6: Oct 20 | B6: Buy real pumpkins + confirm tables/spot (rain plan) | C6: HalloweenPlan
A7: Oct 22 | B7: Lock winter camp dates Dec 24-Jan 7 + fee + min 4/week | C7: WinterCamp + Camp_Plan | E7: Goat theme, Danny designs
A8: Oct 25 | B8: Send price story T1: 400/hr tailor-made, early-bird/royal discount rules in writing | C8: Scripts + Approvals | E8: No public discount
A9: Oct 31 | B9: Halloween event after 15:00 (classes till 15:00) | C9: HalloweenPlan | E9: Big + small pumpkin
A10: Nov 1 | B10: Log every new face into Leads within 24h; T1 to non-clients | C10: Leads + Trials | E10: No lost contacts
A11: Nov 6 | B11: CCA closing gift packs ready: sketchbook + stickers + pen + QR + camp flyer | C11: Events | E11: 30 sets
A12: Nov 10 | B12: Showcase run locked: Sat after 15:00, roles Host/Teacher/Helper | C12: Showcase
A13: Nov 13 | B13: Consents signed + certificates printed for showcase | C13: Consents + Certificates | E13: No signed row, no camera
A14: Nov 13 | B14: Unpaid list cleared before anything new starts | C14: Invoices
